[
  {
    "job_title": "\"탄탄한 중견기업스크랩[토익470점/업계최고복지] 대한항공 국제선 예약/발권센터 전문상담  ZAe4트랜스코스모스코리아서울 강서구 외 5호텔·여행·항공",
    "company_name": "인바운드상담원",
    "location": "여행에이전트",
    "salary": "승무원즉시 지원경력무관•경조사 지원",
    "job_url": "우수사원 포상제도",
    "source_site": "육아휴직",
    "search_keyword": "휴가비 지원",
    "organization_type": "사내 동호회 \"",
    "gtelp_relevance": "발권센터",
    "collection_date": "서울",
    "collection_time": "급여협의"
  },
  {
    "job_title": "\"탄탄한 중견기업스크랩[토익470점/항공예약] 대한항공 국제선 예약/발권센터 전문상담    ZAe4트랜스코스모스코리아서울 강서구 외 5호텔·여행·항공",
    "company_name": "인바운드상담원",
    "location": "여행에이전트",
    "salary": "승무원즉시 지원경력무관09/07(일) 등록•11/04(화) 마감\"",
    "job_url": "발권센터",
    "source_site": "서울",
    "search_keyword": "급여협의",
    "organization_type": "https://www.jobkorea.co.kr/Recruit/GI_Read/47643851?Oem_Code=C1&logpath=1&stext=G-TELP&listno=3&sc=630",
    "gtelp_relevance": "잡코리아",
    "collection_date": "G-TELP",
    "collection_time": "Others"
  },
  {
    "job_title": "\"스크랩[발권안내] 대한항공 국제선 예약발권상담 모집㈜유정에이치알서울 강서구 외 5콜센터·아웃소싱·기타",
    "company_name": "인바운드상담원",
    "location": "아웃바운드상담원",
    "salary": "여행에이전트즉시 지원경력무관•우수사원 포상제도",
    "job_url": "연장근로수당",
    "source_site": "휴일근로수당",
    "search_keyword": "연차제도",
    "organization_type": "퇴직금",
    "gtelp_relevance": "건강보험",
    "collection_date": "고용보험",
    "collection_time": "국민연금"
  },
  {
    "job_title": "\"스크랩[ 강서 대한항공 국제선 발권안내 모집 ]㈜유정에이치알서울 강서구 외 4콜센터·아웃소싱·기타",
    "company_name": "인바운드상담원",
    "location": "여행에이전트",
    "salary": "승무원월급 290~330만원즉시 지원경력무관•우수사원 포상제도",
    "job_url": "연장근로수당",
    "source_site": "휴일근로수당",
    "search_keyword": "연차제도",
    "organization_type": "퇴직금",
    "gtelp_relevance": "건강보험",
    "collection_date": "고용보험",
    "collection_time": "국민연금"
  },
  {
    "job_title": "\"상여금/인센티브 지급스크랩[일반/영어] 대한항공 국내선 예약발권상담 인바운드 모집㈜유정에이치알서울 강서구 외 5콜센터·아웃소싱·기타",
    "company_name": "사무보조",
    "location": "인바운드상담원",
    "salary": "아웃바운드상담원월급 250~290만원즉시 지원경력무관•성과급",
    "job_url": "임직원 할인",
    "source_site": "우수사원 포상제도",
    "search_keyword": "육아휴직",
    "organization_type": "연차제도\"",
    "gtelp_relevance": "콜센터",
    "collection_date": "서울",
    "collection_time": "290만원"
  },
  {
    "job_title": "\"신입 지원 가능스크랩[ 강서구/ 대한항공 국제선 예약/발권 센터 인바운드 상담사 모집]㈜에이치알스카우트서울 강서구 외 5호텔·여행·항공",
    "company_name": "비서",
    "location": "인바운드상담원",
    "salary": "여행에이전트연봉 3",
    "job_url": "500~4",
    "source_site": "500만원즉시 지원신입·경력•신입사원 지원금09/08(월) 등록•상시채용\"",
    "search_keyword": "에이치알스카우트서울 강서구 외 5호텔",
    "organization_type": "서울",
    "gtelp_relevance": "\"4",
    "collection_date": "500만원\"",
    "collection_time": "https://www.jobkorea.co.kr/Recruit/GI_Read/47653510?Oem_Code=C1&logpath=1&stext=G-TELP&listno=14&sc=630"
  },
  {
    "job_title": "\"신입 지원 가능스크랩[ 강서구/ 대한항공 국제선 예약/발권 고객센터 인바운드 상담사 모집]㈜에이치알스카우트서울 강서구 외 5호텔·여행·항공",
    "company_name": "비서",
    "location": "인바운드상담원",
    "salary": "여행에이전트연봉 3",
    "job_url": "500~4",
    "source_site": "500만원즉시 지원신입·경력•경조사 지원",
    "search_keyword": "우수사원 포상제도",
    "organization_type": "휴양시설 지원",
    "gtelp_relevance": "\"",
    "collection_date": "고객센터",
    "collection_time": "서울"
  },
  {
    "job_title": "\"재택/원격근무 가능스크랩최고복지 / 대한항공 국제선 예약발권센터 모집㈜유정에이치알서울 강서구 외 5콜센터·아웃소싱·기타",
    "company_name": "사무보조",
    "location": "인바운드상담원",
    "salary": "아웃바운드상담원즉시 지원경력무관•경조사 지원",
    "job_url": "우수사원 포상제도",
    "source_site": "재택근무",
    "search_keyword": "연장근로수당",
    "organization_type": "휴일근로수당",
    "gtelp_relevance": "연차제도",
    "collection_date": "퇴직금",
    "collection_time": "건강보험\""
  },
  {
    "job_title": "\"신입 지원 가능스크랩마곡나루역 / 대한항공 콜센터 국제선 예약발권상담 [급여&복지우수]에스엠서치플러스㈜서울 강서구 외 5콜센터·아웃소싱·기타",
    "company_name": "사무보조",
    "location": "인바운드상담원",
    "salary": "매장관리자즉시 지원신입·경력•입사축하금",
    "job_url": "주말 휴무09/29(월) 등록•11/28(금) 마감\"",
    "source_site": "콜센터",
    "search_keyword": "서울",
    "organization_type": "급여협의",
    "gtelp_relevance": "https://www.jobkorea.co.kr/Recruit/GI_Read/47783913?Oem_Code=C1&logpath=1&stext=G-TELP&listno=17&sc=630",
    "collection_date": "잡코리아",
    "collection_time": "G-TELP"
  },
  {
    "job_title": "\"스크랩M-07 마곡나루역 [정착금100만] 대한항공 (국제선) 예약/발권 서비스 상담에스엠서치플러스㈜서울 강서구 외 5콜센터·아웃소싱·기타",
    "company_name": "인바운드상담원",
    "location": "아웃바운드상담원",
    "salary": "여행에이전트즉시 지원경력무관09/29(월) 등록•11/28(금) 마감\"",
    "job_url": "콜센터",
    "source_site": "서울",
    "search_keyword": "급여협의",
    "organization_type": "https://www.jobkorea.co.kr/Recruit/GI_Read/47784248?Oem_Code=C1&logpath=1&stext=G-TELP&listno=18&sc=630",
    "gtelp_relevance": "잡코리아",
    "collection_date": "G-TELP",
    "collection_time": "Service"
  },
  {
    "job_title": "\"스크랩M-07 마곡나루 [정착금/구내식당] 대한항공 (국제선) 예약/발권 서비스상담에스엠서치플러스㈜서울 강서구 외 5콜센터·아웃소싱·기타",
    "company_name": "인바운드상담원",
    "location": "아웃바운드상담원",
    "salary": "여행에이전트즉시 지원경력무관•신입사원 지원금09/05(금) 등록•11/04(화) 마감\"",
    "job_url": "콜센터",
    "source_site": "서울",
    "search_keyword": "급여협의",
    "organization_type": "https://www.jobkorea.co.kr/Recruit/GI_Read/47646839?Oem_Code=C1&logpath=1&stext=G-TELP&listno=19&sc=630",
    "gtelp_relevance": "잡코리아",
    "collection_date": "G-TELP",
    "collection_time": "Service"
  },
  {
    "job_title": "\"유연근무제 시행중스크랩[시원스쿨] 실용 영어 컨텐츠 기획자 채용㈜에스제이더블유인터내셔널서울 영등포구학원·어학원·교육원",
    "company_name": "웹기획",
    "location": "교재개발·교수설계즉시 지원경력무관•경조사 지원",
    "salary": "유연근무",
    "job_url": "패밀리데이",
    "source_site": "육아수당",
    "search_keyword": "연차제도",
    "organization_type": "반차제도",
    "gtelp_relevance": "출산휴가",
    "collection_date": "웰컴키트09/18(목) 등록•내일마감\"",
    "collection_time": "시원스쿨"
  },
  {
    "job_title": "\"탄탄한 중견기업스크랩[YBMJIS] 한국국제학교 Business Staff 모집한국국제학교제주 서귀포시학교(초·중·고·대학·특수)",
    "company_name": "총무즉시 지원경력무관•경조사 지원",
    "location": "명절선물/명절상여 지원",
    "salary": "음료/간식 지원",
    "job_url": "점심 식사 지원",
    "source_site": "기숙사 지원10/13(월) 등록•12/12(금)\"",
    "search_keyword": "YBMJIS",
    "organization_type": "제주",
    "gtelp_relevance": "급여협의",
    "collection_date": "https://www.jobkorea.co.kr/Recruit/GI_Read/47831646?Oem_Code=C1&logpath=1&stext=Business+English&listno=8&sc=630",
    "collection_time": "잡코리아"
  },
  {
    "job_title": "\"스크랩[말레이시아] 트레이딩 소프트웨어 해외영업(영어 능통자)Manpower business solution아시아·중동 말레이시아서치펌·헤드헌팅",
    "company_name": "해외영업",
    "location": "금융영업연봉 3",
    "salary": "900~8",
    "job_url": "000만원즉시 지원경력1년↑•숙소 지원",
    "source_site": "연차제도09/30(화) 등록•11/28(금) \"",
    "search_keyword": "말레이시아",
    "organization_type": "전국",
    "gtelp_relevance": "\"8",
    "collection_date": "000만원\"",
    "collection_time": "https://www.jobkorea.co.kr/Recruit/GI_Read/47786442?Oem_Code=C1&logpath=1&stext=Business+English&listno=13&sc=630"
  },
  {
    "job_title": "\"신입 지원 가능스크랩[동국제약] 신입/경력 채용(헬스케어/글로벌/개발/디자인/교육/마케팅 등)동국제약㈜서울 강남구 외 14제약·보건·바이오",
    "company_name": "웹기획",
    "location": "마케팅기획",
    "salary": "브랜드마케터홈페이지 지원신입·경력•경조사 지원",
    "job_url": "음료/간식 지원",
    "source_site": "점심 식사 지원",
    "search_keyword": "우수사원 포상제도",
    "organization_type": "복지포인트\"",
    "gtelp_relevance": "동국제약",
    "collection_date": "서울",
    "collection_time": "급여협의"
  },
  {
    "job_title": "\"스크랩2025年 UNI 무역팀 경력(가공식품 수입/영어) 공채㈜유앤아이트레이드경기 광명시백화점·유통·도소매",
    "company_name": "무역사무원즉시 지원경력09/04(목) 등록•11/03(월) 마감\"",
    "location": "유앤아이트레이드경기 광명시백화점",
    "salary": "경기",
    "job_url": "급여협의",
    "source_site": "https://www.jobkorea.co.kr/Recruit/GI_Read/47635973?Oem_Code=C1&logpath=1&stext=%EC%8B%A4%EB%AC%B4%EC%98%81%EC%96%B4&listno=11&sc=630",
    "search_keyword": "잡코리아",
    "organization_type": "실무영어",
    "gtelp_relevance": "Trading",
    "collection_date": "Medium-High",
    "collection_time": "2025-10-21"
  },
  {
    "job_title": "\"신입 지원 가능스크랩영어 (의료통역 및 병원마케팅) 실무업무㈜닥터뷰서울 서초구광고·홍보·전시",
    "company_name": "마케팅기획",
    "location": "병원코디네이터",
    "salary": "통번역사즉시 지원신입·경력09/23(화) 등록•10/23(목) 마감\"",
    "job_url": "닥터뷰서울 서초구광고",
    "source_site": "서울",
    "search_keyword": "급여협의",
    "organization_type": "https://www.jobkorea.co.kr/Recruit/GI_Read/47750861?Oem_Code=C1&logpath=1&stext=%EC%8B%A4%EB%AC%B4%EC%98%81%EC%96%B4&listno=15&sc=630",
    "gtelp_relevance": "잡코리아",
    "collection_date": "실무영어",
    "collection_time": "Service"
  },
  {
    "job_title": "\"스크랩호텔마케팅 홍보담당자 및 프런트담당자 (해외근무",
    "company_name": "비즈니스영어)㈜크레이블코리아서울 강남구광고·홍보·전시",
    "location": "홍보",
    "salary": "호텔종사자즉시 지원경력09/22(월) 등록•내일마감\"",
    "job_url": "크레이블코리아서울 강남구광고",
    "source_site": "서울",
    "search_keyword": "급여협의",
    "organization_type": "https://www.jobkorea.co.kr/Recruit/GI_Read/47742672?Oem_Code=C1&logpath=1&stext=%EB%B9%84%EC%A6%88%EB%8B%88%EC%8A%A4%EC%98%81%EC%96%B4&listno=1&sc=630",
    "gtelp_relevance": "잡코리아",
    "collection_date": "비즈니스영어",
    "collection_time": "Service"
  },
  {
    "job_title": "\"스크랩[LINGORA] 비즈니스 영어 기업체 출강 강사 채용㈜마켓디자이너스서울 강남구학습지·방문교육",
    "company_name": "학원강사",
    "location": "외국어강사홈페이지 지원경력2년↑09/01(월) 등록•10/31(금) 마감\"",
    "salary": "LINGORA",
    "job_url": "서울",
    "source_site": "급여협의",
    "search_keyword": "https://www.jobkorea.co.kr/Recruit/GI_Read/47607851?Oem_Code=C1&logpath=1&stext=%EB%B9%84%EC%A6%88%EB%8B%88%EC%8A%A4%EC%98%81%EC%96%B4&listno=2&sc=630",
    "organization_type": "잡코리아",
    "gtelp_relevance": "비즈니스영어",
    "collection_date": "Others",
    "collection_time": "Medium"
  },
  {
    "job_title": "\"스크랩브랜드 마케팅 직원 모집 (영어 비즈니스 회화수준 요구)해홍㈜서울 강동구무역·상사",
    "company_name": "경영·비즈니스기획",
    "location": "마케팅기획",
    "salary": "브랜드마케터연봉 3",
    "job_url": "500~4",
    "source_site": "500만원즉시 지원경력1년↑09/10(수) 등록•상시채용\"",
    "search_keyword": "서울 강동구무역",
    "organization_type": "서울",
    "gtelp_relevance": "\"4",
    "collection_date": "500만원\"",
    "collection_time": "https://www.jobkorea.co.kr/Recruit/GI_Read/47677299?Oem_Code=C1&logpath=1&stext=%EB%B9%84%EC%A6%88%EB%8B%88%EC%8A%A4%EC%98%81%EC%96%B4&listno=3&sc=630"
  },
  {
    "job_title": "\"스크랩마케팅 담당자 정규직 모집 (영어 비즈니스 회화수준 요구)해홍㈜서울 강동구무역·상사",
    "company_name": "온라인마케터",
    "location": "홍보연봉 3",
    "salary": "500~4",
    "job_url": "500만원즉시 지원경력1년↑09/05(금) 등록•상시채용\"",
    "source_site": "서울 강동구무역",
    "search_keyword": "서울",
    "organization_type": "\"4",
    "gtelp_relevance": "500만원\"",
    "collection_date": "https://www.jobkorea.co.kr/Recruit/GI_Read/47645194?Oem_Code=C1&logpath=1&stext=%EB%B9%84%EC%A6%88%EB%8B%88%EC%8A%A4%EC%98%81%EC%96%B4&listno=4&sc=630",
    "collection_time": "잡코리아"
  },
  {
    "job_title": "\"스크랩HR 인사 채용 (영어 비즈니스 회화수준 요구)해홍㈜서울 강동구무역·상사",
    "company_name": "인사담당자",
    "location": "헤드헌터연봉 3",
    "salary": "500~4",
    "job_url": "000만원즉시 지원경력1년↑09/05(금) 등록•상시채용\"",
    "source_site": "서울 강동구무역",
    "search_keyword": "서울",
    "organization_type": "\"4",
    "gtelp_relevance": "000만원\"",
    "collection_date": "https://www.jobkorea.co.kr/Recruit/GI_Read/47645306?Oem_Code=C1&logpath=1&stext=%EB%B9%84%EC%A6%88%EB%8B%88%EC%8A%A4%EC%98%81%EC%96%B4&listno=5&sc=630",
    "collection_time": "잡코리아"
  },
  {
    "job_title": "\"스크랩(주)오라컴 Drone 생산관리 채용(영어가능자)㈜오라컴경기 평택시전기·전자·제어",
    "company_name": "해외영업",
    "location": "영업관리",
    "salary": "영업지원즉시 지원경력무관10/13(월) 등록•11/12(수) 마감\"",
    "job_url": "오라컴경기 평택시전기",
    "source_site": "경기",
    "search_keyword": "급여협의",
    "organization_type": "https://www.jobkorea.co.kr/Recruit/GI_Read/47840974?Oem_Code=C1&logpath=1&stext=%EB%B9%84%EC%A6%88%EB%8B%88%EC%8A%A4%EC%98%81%EC%96%B4&listno=9&sc=630",
    "gtelp_relevance": "잡코리아",
    "collection_date": "비즈니스영어",
    "collection_time": "Trading"
  },
  {
    "job_title": "\"스크랩영어 커뮤니케이션 및 번역",
    "company_name": "블록체인 프로젝트 인큐베이션 및 운영㈜샤크테일대전 유성구광고·홍보·전시",
    "location": "해외영업연봉 2",
    "salary": "550만원~즉시 지원경력무관08/25(월) 등록•상시채용\"",
    "job_url": "샤크테일대전 유성구광고",
    "source_site": "대전",
    "search_keyword": "\"연봉 2",
    "organization_type": "550만원\"",
    "gtelp_relevance": "https://www.jobkorea.co.kr/Recruit/GI_Read/47567242?Oem_Code=C1&logpath=1&stext=%EB%B9%84%EC%A6%88%EB%8B%88%EC%8A%A4%EC%98%81%EC%96%B4&listno=11&sc=630",
    "collection_date": "잡코리아",
    "collection_time": "비즈니스영어"
  },
  {
    "job_title": "\"스크랩[Virtedco] Looking for English class instructors  (강원 강릉)㈜버테코강원 강릉시학원·어학원·교육원",
    "company_name": "외국어강사시급 40",
    "location": "000원~즉시 지원경력10/02(목) 등록•11/01(토) 마감\"",
    "salary": "Virtedco",
    "job_url": "강원",
    "source_site": "급여협의",
    "search_keyword": "https://www.jobkorea.co.kr/Recruit/GI_Read/47805056?Oem_Code=C1&logpath=1&stext=%EB%B9%84%EC%A6%88%EB%8B%88%EC%8A%A4%EC%98%81%EC%96%B4&listno=17&sc=630",
    "organization_type": "잡코리아",
    "gtelp_relevance": "비즈니스영어",
    "collection_date": "Others",
    "collection_time": "Medium"
  },
  {
    "job_title": "\"신입 지원 가능스크랩영어능통한분",
    "company_name": "해외무역",
    "location": "㈜프리비아스킨랩서울 성동구생활화학·화장품",
    "salary": "제품영업연봉 2",
    "job_url": "900만원~즉시 지원신입09/15(월) 등록•11/14(금) 마감\"",
    "source_site": "프리비아스킨랩서울 성동구생활화학",
    "search_keyword": "서울",
    "organization_type": "\"연봉 2",
    "gtelp_relevance": "900만원\"",
    "collection_date": "https://www.jobkorea.co.kr/Recruit/GI_Read/47697213?Oem_Code=C1&logpath=1&stext=%EB%B9%84%EC%A6%88%EB%8B%88%EC%8A%A4%EC%98%81%EC%96%B4&listno=18&sc=630",
    "collection_time": "잡코리아"
  },
  {
    "job_title": "\"스크랩수출입무역업무 및 해외자재구매 경력사원 모집㈜태영광학인천 서구반도체·디스플레이·광학",
    "company_name": "구매관리자",
    "location": "무역사무원연봉 3",
    "salary": "400~3",
    "job_url": "900만원즉시 지원경력10/14(화) 등록•10/24(금) 마감\"",
    "source_site": "태영광학인천 서구반도체",
    "search_keyword": "인천",
    "organization_type": "\"3",
    "gtelp_relevance": "900만원\"",
    "collection_date": "https://www.jobkorea.co.kr/Recruit/GI_Read/47851703?Oem_Code=C1&logpath=1&stext=%EB%AC%B4%EC%97%AD%EC%97%85%EB%AC%B4&listno=1&sc=630",
    "collection_time": "잡코리아"
  },
  {
    "job_title": "\"스크랩건설분야] 무역업무 및 코디네이터 (중국어/영어)코템경기 남양주시건설·시공·토목·조경",
    "company_name": "무역사무원",
    "location": "운영보조·매니저",
    "salary": "통번역사즉시 지원경력무관10/14(화) 등록•12/13(토) 마감\"",
    "job_url": "기관명 미상",
    "source_site": "경기",
    "search_keyword": "급여협의",
    "organization_type": "https://www.jobkorea.co.kr/Recruit/GI_Read/47850439?Oem_Code=C1&logpath=1&stext=%EB%AC%B4%EC%97%AD%EC%97%85%EB%AC%B4&listno=2&sc=630",
    "gtelp_relevance": "잡코리아",
    "collection_date": "무역업무",
    "collection_time": "Trading"
  },
  {
    "job_title": "\"스크랩낚시대 무역업무/영업지원 담당자 모집㈜주호상사경기 김포시 외 2생활용품·소비재·기타",
    "company_name": "무역사무원",
    "location": "영업지원즉시 지원경력2년↑10/14(화) 등록•11/13(목) 마감\"",
    "salary": "주호상사경기 김포시 외 2생활용품",
    "job_url": "경기",
    "source_site": "급여협의",
    "search_keyword": "https://www.jobkorea.co.kr/Recruit/GI_Read/47846149?Oem_Code=C1&logpath=1&stext=%EB%AC%B4%EC%97%AD%EC%97%85%EB%AC%B4&listno=3&sc=630",
    "organization_type": "잡코리아",
    "gtelp_relevance": "무역업무",
    "collection_date": "Trading",
    "collection_time": "Medium-High"
  },
  {
    "job_title": "\"스크랩낚시 REEL 무역업무/영업지원 담당자 모집㈜주호상사경기 김포시생활용품·소비재·기타",
    "company_name": "무역사무원",
    "location": "영업지원즉시 지원경력2년↑08/25(월) 등록•10/24(금) 마감\"",
    "salary": "주호상사경기 김포시생활용품",
    "job_url": "경기",
    "source_site": "급여협의",
    "search_keyword": "https://www.jobkorea.co.kr/Recruit/GI_Read/47566878?Oem_Code=C1&logpath=1&stext=%EB%AC%B4%EC%97%AD%EC%97%85%EB%AC%B4&listno=4&sc=630",
    "organization_type": "잡코리아",
    "gtelp_relevance": "무역업무",
    "collection_date": "Trading",
    "collection_time": "Medium-High"
  },
  {
    "job_title": "\"스크랩수입 무역업무",
    "company_name": "영어",
    "location": "중국어 능통 경력자우대피지에스코리아㈜경기 고양시백화점·유통·도소매",
    "salary": "구매관리자",
    "job_url": "유통관리자",
    "source_site": "무역사무원연봉 3",
    "search_keyword": "600~4",
    "organization_type": "000만원즉시 지원경력5년↑10/13(월) 등록•11/12(수) 마감\"",
    "gtelp_relevance": "경기 고양시백화점",
    "collection_date": "경기",
    "collection_time": "\"4"
  },
  {
    "job_title": "\"신입 지원 가능스크랩(주)정우 해외영업 및 무역업무 사원 모집- 중국/동남아 시장 Focus㈜정우부산 강서구무역·상사",
    "company_name": "해외영업연봉 3",
    "location": "500~4",
    "salary": "000만원즉시 지원신입·경력10/16(목) 등록•상시채용\"",
    "job_url": "정우부",
    "source_site": "부산",
    "search_keyword": "\"4",
    "organization_type": "000만원\"",
    "gtelp_relevance": "https://www.jobkorea.co.kr/Recruit/GI_Read/47864146?Oem_Code=C1&logpath=1&stext=%EB%AC%B4%EC%97%AD%EC%97%85%EB%AC%B4&listno=6&sc=630",
    "collection_date": "잡코리아",
    "collection_time": "무역업무"
  },
  {
    "job_title": "\"스크랩해외무역업무 경력 및 신입 직원 채용바운쎌경기 용인시생활화학·화장품",
    "company_name": "해외영업",
    "location": "영업관리",
    "salary": "영업지원즉시 지원경력2년↑10/20(월) 등록•11/19(수) 마감\"",
    "job_url": "기관명 미상",
    "source_site": "경기",
    "search_keyword": "급여협의",
    "organization_type": "https://www.jobkorea.co.kr/Recruit/GI_Read/47883534?Oem_Code=C1&logpath=1&stext=%EB%AC%B4%EC%97%AD%EC%97%85%EB%AC%B4&listno=7&sc=630",
    "gtelp_relevance": "잡코리아",
    "collection_date": "무역업무",
    "collection_time": "Trading"
  },
  {
    "job_title": "\"신입 지원 가능스크랩무역업무 정규직 직원채용국제인터트레이드㈜경기 성남시기계·기계설비",
    "company_name": "사무담당자",
    "location": "총무",
    "salary": "사무보조즉시 지원신입·경력•점심 식사 지원",
    "job_url": "운동비 지원",
    "source_site": "퇴직연금",
    "search_keyword": "건강보험",
    "organization_type": "고용보험",
    "gtelp_relevance": "국민연금",
    "collection_date": "산재보험",
    "collection_time": "공휴일 휴무10/15(수) 등록•11/09(일) 마감\""
  },
  {
    "job_title": "\"신입 지원 가능스크랩[㈜조인엔터프라이즈] 반도체",
    "company_name": "전자 장비 A/S 기술자 및 무역업무 사무직 채용㈜조인엔터프라이즈서울 강남구 외 14건설·시공·토목·조경",
    "location": "사무담당자",
    "salary": "무역사무원",
    "job_url": "영업지원연봉 3",
    "source_site": "000~5",
    "search_keyword": "000만원즉시 지원신입·경력•경조사 지원",
    "organization_type": "연차제도",
    "gtelp_relevance": "퇴직금",
    "collection_date": "건\"",
    "collection_time": "㈜조인엔터프라이즈"
  },
  {
    "job_title": "\"신입 지원 가능스크랩일본무역업무",
    "company_name": "업무지원사원 모집㈜대영계전서울 영등포구백화점·유통·도소매",
    "location": "제품영업",
    "salary": "서비스영업",
    "job_url": "영업지원즉시 지원신입10/13(월) 등록•10/31(금) 마감\"",
    "source_site": "대영계전서울 영등포구백화점",
    "search_keyword": "서울",
    "organization_type": "급여협의",
    "gtelp_relevance": "https://www.jobkorea.co.kr/Recruit/GI_Read/47833337?Oem_Code=C1&logpath=1&stext=%EB%AC%B4%EC%97%AD%EC%97%85%EB%AC%B4&listno=10&sc=630",
    "collection_date": "잡코리아",
    "collection_time": "무역업무"
  },
  {
    "job_title": "\"신입 지원 가능스크랩국내외 전시품 수출입 포워딩/무역업무 직원 모집파나로드경기 고양시 외 11물류·운송·배송",
    "company_name": "유통관리자",
    "location": "무역사무원",
    "salary": "제품영업연봉 3",
    "job_url": "200만원~즉시 지원신입·경력•성과급",
    "source_site": "교통비 지원",
    "search_keyword": "퇴직연금",
    "organization_type": "건강보험",
    "gtelp_relevance": "고용보험",
    "collection_date": "국민연금",
    "collection_time": "산재보험"
  },
  {
    "job_title": "\"스크랩연봉 3400이상) 화장품 의료기기 수출회사 무역 직원 모집 (영어필수)㈜에비에코리아서울 성동구무역·상사",
    "company_name": "무역사무원",
    "location": "해외영업연봉 ~3",
    "salary": "400만원즉시 지원경력2년↑•음료/간식 지원",
    "job_url": "점심 식사 지원",
    "source_site": "임직원 할인",
    "search_keyword": "자율복장",
    "organization_type": "공휴일 휴무10/15(수) 등록•11/14(\"",
    "gtelp_relevance": "에비에코리아서울 성동구무역",
    "collection_date": "서울",
    "collection_time": "\"3"
  },
  {
    "job_title": "\"스크랩TP그룹(구 태평양물산그룹) 의류벤더 일본영업",
    "company_name": "내수영업 경력 채용티피㈜서울 구로구 외 3섬유·의류·패션",
    "location": "해외영업",
    "salary": "법인영업",
    "job_url": "영업관리홈페이지 지원경력2년↑10/15(수) 등록•11/07(금) 마감\"",
    "source_site": "서울 구로구 외 3섬유",
    "search_keyword": "서울",
    "organization_type": "급여협의",
    "gtelp_relevance": "https://www.jobkorea.co.kr/Recruit/GI_Read/47857117?Oem_Code=C1&logpath=1&stext=%ED%95%B4%EC%99%B8%EC%98%81%EC%97%85&listno=1&sc=552",
    "collection_date": "잡코리아",
    "collection_time": "해외영업"
  },
  {
    "job_title": "\"스크랩코스닥 상장사 ㈜딜리 해외기술영업지원",
    "company_name": "해외영업팀(디지털프레스) 담당자 모집㈜딜리경기 동두천시 외 3전기·전자·제어",
    "location": "해외영업",
    "salary": "IT·기술영업",
    "job_url": "영업관리즉시 지원경력•명절선물/명절상여 지원",
    "source_site": "운동시설09/15(월) 등록•10/31(금) 마감\"",
    "search_keyword": "딜리 해외기술영업지원",
    "organization_type": "경기",
    "gtelp_relevance": "급여협의",
    "collection_date": "https://www.jobkorea.co.kr/Recruit/GI_Read/47696974?Oem_Code=C1&logpath=1&stext=%ED%95%B4%EC%99%B8%EC%98%81%EC%97%85&listno=1&sc=630",
    "collection_time": "잡코리아"
  },
  {
    "job_title": "\"많은 지원자가 선택한 인기 공고스크랩㈜유니온 경력 채용 [해외영업",
    "company_name": "수출입",
    "location": "무역]㈜유니온서울 중구금속·재료·자재",
    "salary": "관세사",
    "job_url": "무역사무원",
    "source_site": "제품영업홈페이지 지원경력2년↑•장기근속 포상제도",
    "search_keyword": "기숙사 지원",
    "organization_type": "상해보험",
    "gtelp_relevance": "식사 지원10/13(월) 등록•10/26(일) 마감\"",
    "collection_date": "\"해외영업",
    "collection_time": "수출입"
  },
  {
    "job_title": "\"탄탄한 중견기업스크랩㈜경승 R&D / 해외영업 경력 채용경승서울 강남구 외 9섬유·의류·패션",
    "company_name": "유통관리자",
    "location": "무역사무원",
    "salary": "해외영업즉시 지원경력1년↑10/13(월) 등록•11/12(수) 마감\"",
    "job_url": "경승 R",
    "source_site": "서울",
    "search_keyword": "급여협의",
    "organization_type": "https://www.jobkorea.co.kr/Recruit/GI_Read/47832975?Oem_Code=C1&logpath=1&stext=%ED%95%B4%EC%99%B8%EC%98%81%EC%97%85&listno=3&sc=630",
    "gtelp_relevance": "잡코리아",
    "collection_date": "해외영업",
    "collection_time": "Trading"
  },
  {
    "job_title": "\"신입 지원 가능스크랩2025년 10월 신입사원 수시채용(주)삼양홀딩스경기 성남시화학·에너지·환경",
    "company_name": "마케팅기획",
    "location": "CRM마케터",
    "salary": "해외영업홈페이지 지원신입10/15(수) 등록•10/26(일) 마감\"",
    "job_url": "기관명 미상",
    "source_site": "경기",
    "search_keyword": "급여협의",
    "organization_type": "https://www.jobkorea.co.kr/Recruit/GI_Read/47856840?Oem_Code=C1&logpath=1&stext=%ED%95%B4%EC%99%B8%EC%98%81%EC%97%85&listno=5&sc=630",
    "gtelp_relevance": "잡코리아",
    "collection_date": "해외영업",
    "collection_time": "Trading"
  },
  {
    "job_title": "\"신입 지원 가능스크랩[블랙루즈] BM",
    "company_name": "패키지 디자이너",
    "location": "해외영업지원 (신입/경력)직원 채용㈜디엠앤씨서울 금천구 외 14생활화학·화장품",
    "salary": "경영·비즈니스기획",
    "job_url": "마케팅기획",
    "source_site": "브랜드마케터즉시 지원신입·경력•유연근무",
    "search_keyword": "포상제도",
    "organization_type": "쾌적한 업무공간10/17(금) 등록•11/16(일)\"",
    "gtelp_relevance": "블랙루즈",
    "collection_date": "서울",
    "collection_time": "급여협의"
  },
  {
    "job_title": "\"신입 지원 가능스크랩해외영업팀 상시채용코비코광주 광산구자동차·조선·철강·항공",
    "company_name": "해외영업",
    "location": "영업관리",
    "salary": "영업지원홈페이지 지원신입·경력09/19(금) 등록•상시채용\"",
    "job_url": "기관명 미상",
    "source_site": "광주",
    "search_keyword": "급여협의",
    "organization_type": "https://www.jobkorea.co.kr/Recruit/GI_Read/47734454?Oem_Code=C1&logpath=1&stext=%ED%95%B4%EC%99%B8%EC%98%81%EC%97%85&listno=7&sc=630",
    "gtelp_relevance": "잡코리아",
    "collection_date": "해외영업",
    "collection_time": "Trading"
  },
  {
    "job_title": "\"신입 지원 가능스크랩각 부문 신입/경력사원 모집한국유나이티드제약㈜서울 외 8제약·보건·바이오",
    "company_name": "제품영업",
    "location": "해외영업",
    "salary": "법인영업홈페이지 지원신입·경력10/16(목) 등록•10/26(일) 마감\"",
    "job_url": "서울 외 8제약",
    "source_site": "서울",
    "search_keyword": "급여협의",
    "organization_type": "https://www.jobkorea.co.kr/Recruit/GI_Read/47863682?Oem_Code=C1&logpath=1&stext=%ED%95%B4%EC%99%B8%EC%98%81%EC%97%85&listno=8&sc=630",
    "gtelp_relevance": "잡코리아",
    "collection_date": "해외영업",
    "collection_time": "Trading"
  },
  {
    "job_title": "\"스크랩글로벌 사업부 해외영업팀 화장품 코스메틱 해외영업 담당자㈜이에스인터네셔널서울 강남구생활화학·화장품",
    "company_name": "제품영업",
    "location": "해외영업",
    "salary": "영업지원즉시 지원경력5년↑09/10(수) 등록•상시채용\"",
    "job_url": "사업부",
    "source_site": "서울",
    "search_keyword": "급여협의",
    "organization_type": "https://www.jobkorea.co.kr/Recruit/GI_Read/47677164?Oem_Code=C1&logpath=1&stext=%ED%95%B4%EC%99%B8%EC%98%81%EC%97%85&listno=9&sc=630",
    "gtelp_relevance": "잡코리아",
    "collection_date": "해외영업",
    "collection_time": "Trading"
  },
  {
    "job_title": "\"스크랩코스메틱 화장품 해외 1명 고객관리 해외영업관리 해외영업지원㈜코윈바이오경기 성남시생활화학·화장품",
    "company_name": "해외영업",
    "location": "영업관리",
    "salary": "영업지원즉시 지원경력무관10/14(화) 등록•11/13(목) 마감\"",
    "job_url": "코윈바이오경기 성남시생활화학",
    "source_site": "경기",
    "search_keyword": "급여협의",
    "organization_type": "https://www.jobkorea.co.kr/Recruit/GI_Read/47849004?Oem_Code=C1&logpath=1&stext=%ED%95%B4%EC%99%B8%EC%98%81%EC%97%85&listno=10&sc=630",
    "gtelp_relevance": "잡코리아",
    "collection_date": "해외영업",
    "collection_time": "Trading"
  },
  {
    "job_title": "\"탄탄한 중견기업스크랩해외영업팀 영업인력 채용엠케이전자㈜경기 용인시전기·전자·제어",
    "company_name": "제품영업",
    "location": "해외영업즉시 지원경력10년↑10/13(월) 등록•10/31(금) 마감\"",
    "salary": "경기 용인시전기",
    "job_url": "경기",
    "source_site": "급여협의",
    "search_keyword": "https://www.jobkorea.co.kr/Recruit/GI_Read/47799126?Oem_Code=C1&logpath=1&stext=%ED%95%B4%EC%99%B8%EC%98%81%EC%97%85&listno=11&sc=630",
    "organization_type": "잡코리아",
    "gtelp_relevance": "해외영업",
    "collection_date": "Trading",
    "collection_time": "Low"
  },
  {
    "job_title": "\"신입 지원 가능스크랩[테스] 해외영업팀 채용㈜테스서울 강남구제약·보건·바이오",
    "company_name": "제품영업",
    "location": "서비스영업",
    "salary": "해외영업즉시 지원신입·경력10/13(월) 등록•11/12(수) 마감\"",
    "job_url": "테스서울 강남구제약",
    "source_site": "서울",
    "search_keyword": "급여협의",
    "organization_type": "https://www.jobkorea.co.kr/Recruit/GI_Read/47838633?Oem_Code=C1&logpath=1&stext=%ED%95%B4%EC%99%B8%EC%98%81%EC%97%85&listno=12&sc=630",
    "gtelp_relevance": "잡코리아",
    "collection_date": "해외영업",
    "collection_time": "Trading"
  },
  {
    "job_title": "\"합격축하금 50만원스크랩해외영업팀 사원㈜제이티충남 천안시반도체·디스플레이·광학",
    "company_name": "해외영업즉시 지원경력09/25(목) 등록•10/25(토) 마감\"",
    "location": "제이티충남 천안시반도체",
    "salary": "충남",
    "job_url": "50만원",
    "source_site": "https://www.jobkorea.co.kr/Recruit/GI_Read/47765646?Oem_Code=C1&logpath=1&stext=%ED%95%B4%EC%99%B8%EC%98%81%EC%97%85&listno=13&sc=630",
    "search_keyword": "잡코리아",
    "organization_type": "해외영업",
    "gtelp_relevance": "Trading",
    "collection_date": "Low",
    "collection_time": "2025-10-21"
  },
  {
    "job_title": "\"스크랩[경력] 해외영업팀 해외영업 담당 채용에이치엘엠씨서울 중구백화점·유통·도소매",
    "company_name": "유통관리자",
    "location": "무역사무원",
    "salary": "해외영업즉시 지원경력1년↑10/20(월) 등록•11/19(수) 마감\"",
    "job_url": "기관명 미상",
    "source_site": "서울",
    "search_keyword": "급여협의",
    "organization_type": "https://www.jobkorea.co.kr/Recruit/GI_Read/47887131?Oem_Code=C1&logpath=1&stext=%ED%95%B4%EC%99%B8%EC%98%81%EC%97%85&listno=14&sc=630",
    "gtelp_relevance": "잡코리아",
    "collection_date": "해외영업",
    "collection_time": "Trading"
  },
  {
    "job_title": "\"신입 지원 가능스크랩(주)현대에버다임 해외영업 신입/경력 모집㈜현대에버다임충북 진천군기계·기계설비",
    "company_name": "해외영업즉시 지원신입·경력1년↑09/23(화) 등록•10/23(목) 마감\"",
    "location": "현대에버다임충북 진천군기계",
    "salary": "충북",
    "job_url": "급여협의",
    "source_site": "https://www.jobkorea.co.kr/Recruit/GI_Read/47751988?Oem_Code=C1&logpath=1&stext=%ED%95%B4%EC%99%B8%EC%98%81%EC%97%85&listno=15&sc=630",
    "search_keyword": "잡코리아",
    "organization_type": "해외영업",
    "gtelp_relevance": "Trading",
    "collection_date": "Low",
    "collection_time": "2025-10-21"
  },
  {
    "job_title": "\"탄탄한 중견기업스크랩(주)약진통상 해외영업 경력 채용㈜약진통상서울 송파구섬유·의류·패션",
    "company_name": "무역사무원",
    "location": "해외영업즉시 지원경력2년↑10/16(목) 등록•10/31(금) 마감\"",
    "salary": "약진통상서울 송파구섬유",
    "job_url": "서울",
    "source_site": "급여협의",
    "search_keyword": "https://www.jobkorea.co.kr/Recruit/GI_Read/47863278?Oem_Code=C1&logpath=1&stext=%ED%95%B4%EC%99%B8%EC%98%81%EC%97%85&listno=16&sc=630",
    "organization_type": "잡코리아",
    "gtelp_relevance": "해외영업",
    "collection_date": "Trading",
    "collection_time": "Medium-High"
  },
  {
    "job_title": "\"신입 지원 가능스크랩(주)다비오 해외영업지원 담당자 채용㈜다비오서울 마포구솔루션·SI·CRM·ERP",
    "company_name": "해외영업",
    "location": "법인영업",
    "salary": "IT·기술영업즉시 지원신입·경력10/02(목) 등록•11/01(토) 마감\"",
    "job_url": "다비오서울 마포구솔루션",
    "source_site": "서울",
    "search_keyword": "급여협의",
    "organization_type": "https://www.jobkorea.co.kr/Recruit/GI_Read/47805804?Oem_Code=C1&logpath=1&stext=%ED%95%B4%EC%99%B8%EC%98%81%EC%97%85&listno=17&sc=630",
    "gtelp_relevance": "잡코리아",
    "collection_date": "해외영업",
    "collection_time": "Trading"
  },
  {
    "job_title": "\"신입 지원 가능스크랩해외영업 직무 신입/경력사원 모집㈜제뉴원사이언스서울 중구제약·보건·바이오",
    "company_name": "제품영업",
    "location": "해외영업",
    "salary": "법인영업홈페이지 지원신입·경력3년↑10/17(금) 등록•10/26(일) 마감\"",
    "job_url": "제뉴원사이언스서울 중구제약",
    "source_site": "서울",
    "search_keyword": "급여협의",
    "organization_type": "https://www.jobkorea.co.kr/Recruit/GI_Read/47872494?Oem_Code=C1&logpath=1&stext=%ED%95%B4%EC%99%B8%EC%98%81%EC%97%85&listno=18&sc=630",
    "gtelp_relevance": "잡코리아",
    "collection_date": "해외영업",
    "collection_time": "Trading"
  },
  {
    "job_title": "\"스크랩해외영업 마케팅 직원 채용㈜펠리테크서울 송파구생활용품·소비재·기타",
    "company_name": "해외영업월급 250만원~즉시 지원경력무관10/17(금) 등록•11/16(일) 마감\"",
    "location": "펠리테크서울 송파구생활용품",
    "salary": "서울",
    "job_url": "월급 250만원",
    "source_site": "https://www.jobkorea.co.kr/Recruit/GI_Read/47877422?Oem_Code=C1&logpath=1&stext=%ED%95%B4%EC%99%B8%EC%98%81%EC%97%85&listno=19&sc=630",
    "search_keyword": "잡코리아",
    "organization_type": "해외영업",
    "gtelp_relevance": "Trading",
    "collection_date": "Low",
    "collection_time": "2025-10-21"
  },
  {
    "job_title": "\"탄탄한 중견기업스크랩(주)풍인무역 해외영업 경력 채용 (베트남 주재원)㈜풍인무역아시아·중동 베트남섬유·의류·패션",
    "company_name": "무역사무원",
    "location": "해외영업",
    "salary": "영업관리즉시 지원경력3년↑10/14(화) 등록•11/13(목) 마감\"",
    "job_url": "풍인무역아시아",
    "source_site": "전국",
    "search_keyword": "급여협의",
    "organization_type": "https://www.jobkorea.co.kr/Recruit/GI_Read/47851290?Oem_Code=C1&logpath=1&stext=%ED%95%B4%EC%99%B8%EC%98%81%EC%97%85&listno=20&sc=630",
    "gtelp_relevance": "잡코리아",
    "collection_date": "해외영업",
    "collection_time": "Trading"
  },
  {
    "job_title": "\"스크랩International Sales Representative 반도체 해외영업스미스앤어소시에이트코리아서울 강남구백화점·유통·도소매",
    "company_name": "서비스영업",
    "location": "해외영업연봉 40",
    "salary": "000~80",
    "job_url": "000만원즉시 지원경력2년↑09/23(화) 등록•10/23(목) 마감\"",
    "source_site": "기관명 미상",
    "search_keyword": "서울",
    "organization_type": "\"80",
    "gtelp_relevance": "000만원\"",
    "collection_date": "https://www.jobkorea.co.kr/Recruit/GI_Read/47753818?Oem_Code=C1&logpath=1&stext=International+business&listno=13&sc=630",
    "collection_time": "잡코리아"
  },
  {
    "job_title": "\"스크랩International Sales Manager 반도체 해외영업스미스앤어소시에이트코리아서울 강남구백화점·유통·도소매",
    "company_name": "서비스영업",
    "location": "해외영업연봉 40",
    "salary": "000~80",
    "job_url": "000만원즉시 지원경력7년↑09/23(화) 등록•10/23(목) 마감\"",
    "source_site": "기관명 미상",
    "search_keyword": "서울",
    "organization_type": "\"80",
    "gtelp_relevance": "000만원\"",
    "collection_date": "https://www.jobkorea.co.kr/Recruit/GI_Read/47753842?Oem_Code=C1&logpath=1&stext=International+business&listno=19&sc=630",
    "collection_time": "잡코리아"
  },
  {
    "job_title": "\"신입 지원 가능스크랩[데이빗의 영어회화] 1:1 성인 영어 회화 선생님 모집 (합정역)데이빗의 영어회화서울 마포구학원·어학원·교육원",
    "company_name": "학원강사",
    "location": "외국어강사월급 350만원~즉시 지원신입·경력10/13(월) 등록•11/12(수) 마감\"",
    "salary": "데이빗의 영어회화",
    "job_url": "서울",
    "source_site": "월급 350만원",
    "search_keyword": "https://www.jobkorea.co.kr/Recruit/GI_Read/47839648?Oem_Code=C1&logpath=1&stext=%EC%98%81%EC%96%B4%ED%9A%8C%ED%99%94&listno=1&sc=630",
    "organization_type": "잡코리아",
    "gtelp_relevance": "영어회화",
    "collection_date": "Others",
    "collection_time": "Medium"
  },
  {
    "job_title": "\"신입 지원 가능스크랩영어회화 강사모집평택어학원경기 평택시학원·어학원·교육원",
    "company_name": "학원강사",
    "location": "외국어강사시급 20",
    "salary": "000원~즉시 지원신입10/10(금) 등록•12/09(화) 마감\"",
    "job_url": "기관명 미상",
    "source_site": "경기",
    "search_keyword": "급여협의",
    "organization_type": "https://www.jobkorea.co.kr/Recruit/GI_Read/47824991?Oem_Code=C1&logpath=1&stext=%EC%98%81%EC%96%B4%ED%9A%8C%ED%99%94&listno=2&sc=630",
    "gtelp_relevance": "잡코리아",
    "collection_date": "영어회화",
    "collection_time": "Others"
  },
  {
    "job_title": "\"스크랩영어회화강사리딩비영어독서학원경기 용인시학원·어학원·교육원",
    "company_name": "외국어강사시급 15",
    "location": "000원~즉시 지원경력무관10/13(월) 등록•11/12(수) 마감\"",
    "salary": "기관명 미상",
    "job_url": "경기",
    "source_site": "급여협의",
    "search_keyword": "https://www.jobkorea.co.kr/Recruit/GI_Read/47836053?Oem_Code=C1&logpath=1&stext=%EC%98%81%EC%96%B4%ED%9A%8C%ED%99%94&listno=3&sc=630",
    "organization_type": "잡코리아",
    "gtelp_relevance": "영어회화",
    "collection_date": "Others",
    "collection_time": "Medium"
  },
  {
    "job_title": "\"신입 지원 가능스크랩평택 영어회화 강사㈜세라스클래스경기 평택시학원·어학원·교육원",
    "company_name": "학원강사시급 23",
    "location": "000원~즉시 지원신입·경력09/27(토) 등록•10/26(일) 마감\"",
    "salary": "세라스클래스경기 평택시학원",
    "job_url": "경기",
    "source_site": "급여협의",
    "search_keyword": "https://www.jobkorea.co.kr/Recruit/GI_Read/47775960?Oem_Code=C1&logpath=1&stext=%EC%98%81%EC%96%B4%ED%9A%8C%ED%99%94&listno=4&sc=630",
    "organization_type": "잡코리아",
    "gtelp_relevance": "영어회화",
    "collection_date": "Others",
    "collection_time": "Medium"
  },
  {
    "job_title": "\"상여금/인센티브 지급스크랩[성인영어회화강사 ] 파트타임 강사채용더플레이스이(The Place E)서울 마포구학원·어학원·교육원",
    "company_name": "학원강사즉시 지원경력1년↑•인센티브 제도10/18(토) 등록•11/30(일) 마감\"",
    "location": "성인영어회화강사",
    "salary": "서울",
    "job_url": "급여협의",
    "source_site": "https://www.jobkorea.co.kr/Recruit/GI_Read/47878147?Oem_Code=C1&logpath=1&stext=%EC%98%81%EC%96%B4%ED%9A%8C%ED%99%94&listno=5&sc=630",
    "search_keyword": "잡코리아",
    "organization_type": "영어회화",
    "gtelp_relevance": "Others",
    "collection_date": "Medium",
    "collection_time": "2025-10-21"
  },
  {
    "job_title": "\"스크랩[인천] 대학교 영어회화 강사 구인㈜버테코에듀인천 동구학원·어학원·교육원",
    "company_name": "외국어강사즉시 지원경력3년↑09/24(수) 등록•10/24(금) 마감\"",
    "location": "버테코에듀인천 동구학원",
    "salary": "인천",
    "job_url": "급여협의",
    "source_site": "https://www.jobkorea.co.kr/Recruit/GI_Read/47759762?Oem_Code=C1&logpath=1&stext=%EC%98%81%EC%96%B4%ED%9A%8C%ED%99%94&listno=6&sc=630",
    "search_keyword": "잡코리아",
    "organization_type": "영어회화",
    "gtelp_relevance": "University",
    "collection_date": "Medium",
    "collection_time": "2025-10-21"
  },
  {
    "job_title": "\"스크랩동탄2 유일영어 성인 영어회화강사 채용유일영어경기 화성시학원·어학원·교육원",
    "company_name": "학원강사즉시 지원경력무관09/06(토) 등록•11/04(화) 마감\"",
    "location": "기관명 미상",
    "salary": "경기",
    "job_url": "급여협의",
    "source_site": "https://www.jobkorea.co.kr/Recruit/GI_Read/47649526?Oem_Code=C1&logpath=1&stext=%EC%98%81%EC%96%B4%ED%9A%8C%ED%99%94&listno=7&sc=630",
    "search_keyword": "잡코리아",
    "organization_type": "영어회화",
    "gtelp_relevance": "Others",
    "collection_date": "Medium",
    "collection_time": "2025-10-21"
  },
  {
    "job_title": "\"신입 지원 가능스크랩[데이빗의 영어회화] 학원 운영 매니저(Executive Assistant) 모집데이빗의 영어회화서울 마포구학원·어학원·교육원",
    "company_name": "학원상담·운영시급 12",
    "location": "000원~즉시 지원신입·경력10/17(금) 등록•11/15(토) 마감\"",
    "salary": "데이빗의 영어회화",
    "job_url": "서울",
    "source_site": "급여협의",
    "search_keyword": "https://www.jobkorea.co.kr/Recruit/GI_Read/47869073?Oem_Code=C1&logpath=1&stext=%EC%98%81%EC%96%B4%ED%9A%8C%ED%99%94&listno=8&sc=630",
    "organization_type": "잡코리아",
    "gtelp_relevance": "영어회화",
    "collection_date": "Others",
    "collection_time": "Medium"
  },
  {
    "job_title": "\"신입 지원 가능스크랩영어회화 1:1 강사님 모집맨하탄 어학원부산 부산진구학원·어학원·교육원",
    "company_name": "외국어강사즉시 지원신입·경력1년↑10/13(월) 등록•11/12(수) 마감\"",
    "location": "어학원부",
    "salary": "부산",
    "job_url": "급여협의",
    "source_site": "https://www.jobkorea.co.kr/Recruit/GI_Read/47841274?Oem_Code=C1&logpath=1&stext=%EC%98%81%EC%96%B4%ED%9A%8C%ED%99%94&listno=9&sc=630",
    "search_keyword": "잡코리아",
    "organization_type": "영어회화",
    "gtelp_relevance": "Others",
    "collection_date": "Medium",
    "collection_time": "2025-10-21"
  },
  {
    "job_title": "\"스크랩민병철어학원(부천점) 영어회화 강사 모집합니다㈜부천민병철어학원경기 부천시학원·어학원·교육원",
    "company_name": "외국어강사즉시 지원경력1년↑09/26(금) 등록•10/26(일) 마감\"",
    "location": "부천민병철어학원경기 부천시학원",
    "salary": "경기",
    "job_url": "급여협의",
    "source_site": "https://www.jobkorea.co.kr/Recruit/GI_Read/47769223?Oem_Code=C1&logpath=1&stext=%EC%98%81%EC%96%B4%ED%9A%8C%ED%99%94&listno=10&sc=630",
    "search_keyword": "잡코리아",
    "organization_type": "영어회화",
    "gtelp_relevance": "Others",
    "collection_date": "Medium",
    "collection_time": "2025-10-21"
  },
  {
    "job_title": "\"스크랩성인 영어회화 주말(토요일) 강사 구인합니다.(JC)글로벌어학원인천 부평구학원·어학원·교육원",
    "company_name": "외국어강사시급 17",
    "location": "000원~즉시 지원경력무관10/15(수) 등록•11/14(금) 마감\"",
    "salary": "기관명 미상",
    "job_url": "인천",
    "source_site": "급여협의",
    "search_keyword": "https://www.jobkorea.co.kr/Recruit/GI_Read/47860006?Oem_Code=C1&logpath=1&stext=%EC%98%81%EC%96%B4%ED%9A%8C%ED%99%94&listno=11&sc=630",
    "organization_type": "잡코리아",
    "gtelp_relevance": "영어회화",
    "collection_date": "Others",
    "collection_time": "Medium"
  },
  {
    "job_title": "\"믿고보는 대기업스크랩[YBM인천센터] 기초영어회화 전문 강사 모집YBM인천어학원인천 부평구학원·어학원·교육원",
    "company_name": "외국어강사즉시 지원경력무관09/23(화) 등록•10/23(목) 마감\"",
    "location": "인천센터",
    "salary": "인천",
    "job_url": "급여협의",
    "source_site": "https://www.jobkorea.co.kr/Recruit/GI_Read/47747991?Oem_Code=C1&logpath=1&stext=%EC%98%81%EC%96%B4%ED%9A%8C%ED%99%94&listno=12&sc=630",
    "search_keyword": "잡코리아",
    "organization_type": "영어회화",
    "gtelp_relevance": "Others",
    "collection_date": "Medium",
    "collection_time": "2025-10-21"
  },
  {
    "job_title": "\"스크랩송도맨하탄성인어학원  오픽 영어회화강사 모집송도맨하탄성인어학원인천 연수구학원·어학원·교육원",
    "company_name": "외국어강사시급 23",
    "location": "000원~즉시 지원경력무관09/25(목) 등록•10/25(토) 마감\"",
    "salary": "기관명 미상",
    "job_url": "인천",
    "source_site": "급여협의",
    "search_keyword": "https://www.jobkorea.co.kr/Recruit/GI_Read/47769015?Oem_Code=C1&logpath=1&stext=%EC%98%81%EC%96%B4%ED%9A%8C%ED%99%94&listno=13&sc=630",
    "organization_type": "잡코리아",
    "gtelp_relevance": "영어회화",
    "collection_date": "Others",
    "collection_time": "Medium"
  },
  {
    "job_title": "\"스크랩[군자역] 일대일 영어회화 강사 모집프랙톡 통역학원서울 광진구학원·어학원·교육원",
    "company_name": "외국어강사즉시 지원경력무관10/13(월) 등록•11/12(수) 마감\"",
    "location": "군자역",
    "salary": "서울",
    "job_url": "급여협의",
    "source_site": "https://www.jobkorea.co.kr/Recruit/GI_Read/47842099?Oem_Code=C1&logpath=1&stext=%EC%98%81%EC%96%B4%ED%9A%8C%ED%99%94&listno=14&sc=630",
    "search_keyword": "잡코리아",
    "organization_type": "영어회화",
    "gtelp_relevance": "Others",
    "collection_date": "Medium",
    "collection_time": "2025-10-21"
  },
  {
    "job_title": "\"스크랩SOPHIA CLASS 평택 성인전문 영어회화 소피아클래스 비율제 강사 채용소피아 클래스경기 평택시학원·어학원·교육원",
    "company_name": "학원강사",
    "location": "외국어강사시급 30",
    "salary": "000원~즉시 지원경력무관08/28(목) 등록•상시채용\"",
    "job_url": "기관명 미상",
    "source_site": "경기",
    "search_keyword": "급여협의",
    "organization_type": "https://www.jobkorea.co.kr/Recruit/GI_Read/47587648?Oem_Code=C1&logpath=1&stext=%EC%98%81%EC%96%B4%ED%9A%8C%ED%99%94&listno=15&sc=630",
    "gtelp_relevance": "잡코리아",
    "collection_date": "영어회화",
    "collection_time": "Others"
  },
  {
    "job_title": "\"스크랩민병철어학원(부천점) 일대일/출강 강사(토익/영어회화) 모집㈜부천민병철어학원경기 부천시학원·어학원·교육원",
    "company_name": "학원강사즉시 지원경력1년↑10/15(수) 등록•11/14(금) 마감\"",
    "location": "부천민병철어학원경기 부천시학원",
    "salary": "경기",
    "job_url": "급여협의",
    "source_site": "https://www.jobkorea.co.kr/Recruit/GI_Read/47855415?Oem_Code=C1&logpath=1&stext=%EC%98%81%EC%96%B4%ED%9A%8C%ED%99%94&listno=16&sc=630",
    "search_keyword": "잡코리아",
    "organization_type": "영어회화",
    "gtelp_relevance": "Others",
    "collection_date": "Medium",
    "collection_time": "2025-10-21"
  },
  {
    "job_title": "\"탄탄한 중견기업스크랩영어회화강사(화상/전화) 재택(해외거주가능)동화세상에듀코서울 동대문구학습지·방문교육",
    "company_name": "학습지·방문교사즉시 지원경력무관•주40시간10/16(목) 등록•11/15(토) 마감\"",
    "location": "기관명 미상",
    "salary": "서울",
    "job_url": "급여협의",
    "source_site": "https://www.jobkorea.co.kr/Recruit/GI_Read/47863957?Oem_Code=C1&logpath=1&stext=%EC%98%81%EC%96%B4%ED%9A%8C%ED%99%94&listno=17&sc=630",
    "search_keyword": "잡코리아",
    "organization_type": "영어회화",
    "gtelp_relevance": "Others",
    "collection_date": "Medium",
    "collection_time": "2025-10-21"
  },
  {
    "job_title": "\"유연근무제 시행중스크랩영어회화 강사모집오피아어학원(송도점)인천 연수구학원·어학원·교육원",
    "company_name": "학원강사",
    "location": "외국어강사즉시 지원경력무관•유연근무10/20(월) 등록•11/19(수) 마감\"",
    "salary": "기관명 미상",
    "job_url": "인천",
    "source_site": "급여협의",
    "search_keyword": "https://www.jobkorea.co.kr/Recruit/GI_Read/47888281?Oem_Code=C1&logpath=1&stext=%EC%98%81%EC%96%B4%ED%9A%8C%ED%99%94&listno=18&sc=630",
    "organization_type": "잡코리아",
    "gtelp_relevance": "영어회화",
    "collection_date": "Others",
    "collection_time": "Medium"
  },
  {
    "job_title": "\"신입 지원 가능스크랩영어회화",
    "company_name": "영문법 강사모집평택어학원경기 평택시학원·어학원·교육원",
    "location": "학원강사",
    "salary": "외국어강사시급 20",
    "job_url": "000원~즉시 지원신입10/10(금) 등록•11/09(일) 마감\"",
    "source_site": "기관명 미상",
    "search_keyword": "경기",
    "organization_type": "급여협의",
    "gtelp_relevance": "https://www.jobkorea.co.kr/Recruit/GI_Read/47825246?Oem_Code=C1&logpath=1&stext=%EC%98%81%EC%96%B4%ED%9A%8C%ED%99%94&listno=19&sc=630",
    "collection_date": "잡코리아",
    "collection_time": "영어회화"
  },
  {
    "job_title": "\"스크랩온라인 영어회화학원 교육 팀장예리엘잉글리쉬서울 금천구학원·어학원·교육원",
    "company_name": "온라인마케터",
    "location": "학원상담·운영즉시 지원경력09/13(토) 등록•11/12(수) 마감\"",
    "salary": "기관명 미상",
    "job_url": "서울",
    "source_site": "급여협의",
    "search_keyword": "https://www.jobkorea.co.kr/Recruit/GI_Read/47694225?Oem_Code=C1&logpath=1&stext=%EC%98%81%EC%96%B4%ED%9A%8C%ED%99%94&listno=20&sc=630",
    "organization_type": "잡코리아",
    "gtelp_relevance": "영어회화",
    "collection_date": "Others",
    "collection_time": "Medium"
  },
  {
    "job_title": "[업계최고복지] 대한항공 국제선 예약발권 전문상담 채용 KAe4",
    "company_name": "(주)트랜스코스모스코리아",
    "location": "서울",
    "salary": "급여협의",
    "job_url": "https://www.saramin.co.kr/zf_user/jobs/relay/view?view_type=search&rec_idx=51963673&location=ts&searchword=G-TELP&searchType=1&paid_fl=n&search_uuid=ce4dbbb1-92c1-493e-a4d2-0856468f5958",
    "source_site": "사람인",
    "search_keyword": "G-TELP",
    "organization_type": "Others",
    "gtelp_relevance": "Low",
    "collection_date": "2025-10-21",
    "collection_time": "15:27:06"
  },
  {
    "job_title": "[ 강서구 / 대한항공 국제선 예약/발권센터 상담사 모집]",
    "company_name": "(주)에이치알스카우트",
    "location": "서울",
    "salary": "급여협의",
    "job_url": "https://www.saramin.co.kr/zf_user/jobs/relay/view?view_type=search&rec_idx=51926383&location=ts&searchword=G-TELP&searchType=1&paid_fl=n&search_uuid=ce4dbbb1-92c1-493e-a4d2-0856468f5958",
    "source_site": "사람인",
    "search_keyword": "G-TELP",
    "organization_type": "Others",
    "gtelp_relevance": "Low",
    "collection_date": "2025-10-21",
    "collection_time": "15:27:06"
  },
  {
    "job_title": "[시원스쿨] 실용 영어 컨텐츠 기획자 채용",
    "company_name": "(주)에스제이더블유인터내셔널",
    "location": "서울",
    "salary": "급여협의",
    "job_url": "https://www.saramin.co.kr/zf_user/jobs/relay/view?view_type=search&rec_idx=51862749&location=ts&searchword=%EC%A7%80%ED%85%94%ED%94%84&searchType=1&paid_fl=n&search_uuid=b3cc64a3-276d-4829-8d73-933b60eb3cab",
    "source_site": "사람인",
    "search_keyword": "지텔프",
    "organization_type": "Others",
    "gtelp_relevance": "Medium",
    "collection_date": "2025-10-21",
    "collection_time": "15:27:10"
  },
  {
    "job_title": "[시원스쿨]한국어·영어 능통 외국인 한국어 강사 채용",
    "company_name": "(주)에스제이더블유인터내셔널",
    "location": "서울",
    "salary": "급여협의",
    "job_url": "https://www.saramin.co.kr/zf_user/jobs/relay/view?view_type=search&rec_idx=51862919&location=ts&searchword=%EC%A7%80%ED%85%94%ED%94%84&searchType=1&paid_fl=n&search_uuid=b3cc64a3-276d-4829-8d73-933b60eb3cab",
    "source_site": "사람인",
    "search_keyword": "지텔프",
    "organization_type": "Others",
    "gtelp_relevance": "Medium",
    "collection_date": "2025-10-21",
    "collection_time": "15:27:10"
  },
  {
    "job_title": "[주류/F&B/비즈니스영어/해당경력5년이상/BM] 브랜드 매니저",
    "company_name": "(주)메이븐앤컴퍼니",
    "location": "서울",
    "salary": "급여협의",
    "job_url": "https://www.saramin.co.kr/zf_user/jobs/relay/view?view_type=search&rec_idx=52026906&location=ts&searchword=Business+English&searchType=1&paid_fl=n&search_uuid=34e5c2ed-0f96-4882-a531-8a63653cb5dd",
    "source_site": "사람인",
    "search_keyword": "Business English",
    "organization_type": "Others",
    "gtelp_relevance": "High",
    "collection_date": "2025-10-21",
    "collection_time": "15:27:14"
  },
  {
    "job_title": "역직구 이커머스 기획 및 운영 담당 채용/비즈니스 영어 가능자",
    "company_name": "(주)쇼럽",
    "location": "서울",
    "salary": "급여협의",
    "job_url": "https://www.saramin.co.kr/zf_user/jobs/relay/view?view_type=search&rec_idx=51992884&location=ts&searchword=Business+English&searchType=1&paid_fl=n&search_uuid=34e5c2ed-0f96-4882-a531-8a63653cb5dd",
    "source_site": "사람인",
    "search_keyword": "Business English",
    "organization_type": "Others",
    "gtelp_relevance": "Medium",
    "collection_date": "2025-10-21",
    "collection_time": "15:27:14"
  },
  {
    "job_title": "[패숀팩토리] 글로벌사업팀 모집 비즈니스 영어능력 필수",
    "company_name": "패숀팩토리",
    "location": "서울",
    "salary": "급여협의",
    "job_url": "https://www.saramin.co.kr/zf_user/jobs/relay/view?view_type=search&rec_idx=52095877&location=ts&searchword=Business+English&searchType=1&paid_fl=n&search_uuid=34e5c2ed-0f96-4882-a531-8a63653cb5dd",
    "source_site": "사람인",
    "search_keyword": "Business English",
    "organization_type": "Others",
    "gtelp_relevance": "Medium",
    "collection_date": "2025-10-21",
    "collection_time": "15:27:14"
  },
  {
    "job_title": "[섬유/영어/무역실무/섬유화학] 해외 영업 경력직",
    "company_name": "(주)메이븐앤컴퍼니",
    "location": "서울",
    "salary": "급여협의",
    "job_url": "https://www.saramin.co.kr/zf_user/jobs/relay/view?view_type=search&rec_idx=52077033&location=ts&searchword=%EC%8B%A4%EB%AC%B4%EC%98%81%EC%96%B4&searchType=1&paid_fl=n&search_uuid=8901eab2-93c2-4390-90fb-a04acb65d846",
    "source_site": "사람인",
    "search_keyword": "실무영어",
    "organization_type": "Trading",
    "gtelp_relevance": "Medium-High",
    "collection_date": "2025-10-21",
    "collection_time": "15:27:17"
  },
  {
    "job_title": "[동국제약] 신입/경력 채용(헬스케어/글로벌/개발/디자인/교육/마케팅 등) ~ 10/29",
    "company_name": "동국제약(주)",
    "location": "서울",
    "salary": "급여협의",
    "job_url": "https://www.saramin.co.kr/zf_user/jobs/relay/view?view_type=search&rec_idx=52081069&location=ts&searchword=%EB%B9%84%EC%A6%88%EB%8B%88%EC%8A%A4%EC%98%81%EC%96%B4&searchType=1&paid_fl=n&search_uuid=ad98cbdf-1481-4bf7-80ea-6db651ae9511",
    "source_site": "사람인",
    "search_keyword": "비즈니스영어",
    "organization_type": "IT_Tech",
    "gtelp_relevance": "Low",
    "collection_date": "2025-10-21",
    "collection_time": "15:27:21"
  },
  {
    "job_title": "[(주)티에이치엔] 해외무역업무담당자 모집",
    "company_name": "(주)티에이치엔",
    "location": "대구",
    "salary": "급여협의",
    "job_url": "https://www.saramin.co.kr/zf_user/jobs/relay/view?view_type=search&rec_idx=52012956&location=ts&searchword=%EB%AC%B4%EC%97%AD%EC%97%85%EB%AC%B4&searchType=1&paid_fl=n&search_uuid=bda5d4d8-f57d-4b49-a8fc-e2eebec4d66d",
    "source_site": "사람인",
    "search_keyword": "무역업무",
    "organization_type": "Trading",
    "gtelp_relevance": "Medium-High",
    "collection_date": "2025-10-21",
    "collection_time": "15:27:23"
  },
  {
    "job_title": "㈜학산 신발 제조업무역업무직 모집",
    "company_name": "(주)학산",
    "location": "부산",
    "salary": "급여협의",
    "job_url": "https://www.saramin.co.kr/zf_user/jobs/relay/view?view_type=search&rec_idx=52054468&location=ts&searchword=%EB%AC%B4%EC%97%AD%EC%97%85%EB%AC%B4&searchType=1&paid_fl=n&search_uuid=bda5d4d8-f57d-4b49-a8fc-e2eebec4d66d",
    "source_site": "사람인",
    "search_keyword": "무역업무",
    "organization_type": "Trading",
    "gtelp_relevance": "Medium-High",
    "collection_date": "2025-10-21",
    "collection_time": "15:27:23"
  },
  {
    "job_title": "\"기술직 및무역업무",
    "company_name": "회계 신입/경력 모집\"",
    "location": "대원이노베이션(주)",
    "salary": "경기",
    "job_url": "급여협의",
    "source_site": "https://www.saramin.co.kr/zf_user/jobs/relay/view?view_type=search&rec_idx=51959044&location=ts&searchword=%EB%AC%B4%EC%97%AD%EC%97%85%EB%AC%B4&searchType=1&paid_fl=n&search_uuid=bda5d4d8-f57d-4b49-a8fc-e2eebec4d66d",
    "search_keyword": "사람인",
    "organization_type": "무역업무",
    "gtelp_relevance": "Trading",
    "collection_date": "Medium-High",
    "collection_time": "2025-10-21"
  },
  {
    "job_title": "무역업무정규직 채용",
    "company_name": "국제인터트레이드(주)",
    "location": "경기",
    "salary": "급여협의",
    "job_url": "https://www.saramin.co.kr/zf_user/jobs/relay/view?view_type=search&rec_idx=52045204&location=ts&searchword=%EB%AC%B4%EC%97%AD%EC%97%85%EB%AC%B4&searchType=1&paid_fl=n&search_uuid=bda5d4d8-f57d-4b49-a8fc-e2eebec4d66d",
    "source_site": "사람인",
    "search_keyword": "무역업무",
    "organization_type": "Trading",
    "gtelp_relevance": "Medium-High",
    "collection_date": "2025-10-21",
    "collection_time": "15:27:23"
  },
  {
    "job_title": "2025년 하반기무역업무담당자 신입&경력 채용공고",
    "company_name": "(주)건백",
    "location": "경북",
    "salary": "\"3",
    "job_url": "100 만원\"",
    "source_site": "https://www.saramin.co.kr/zf_user/jobs/relay/view?view_type=search&rec_idx=52044708&location=ts&searchword=%EB%AC%B4%EC%97%AD%EC%97%85%EB%AC%B4&searchType=1&paid_fl=n&search_uuid=bda5d4d8-f57d-4b49-a8fc-e2eebec4d66d",
    "search_keyword": "사람인",
    "organization_type": "무역업무",
    "gtelp_relevance": "Trading",
    "collection_date": "Medium-High",
    "collection_time": "2025-10-21"
  },
  {
    "job_title": "무역업무실무자 모집",
    "company_name": "(주)토스템",
    "location": "서울",
    "salary": "급여협의",
    "job_url": "https://www.saramin.co.kr/zf_user/jobs/relay/view?view_type=search&rec_idx=52088754&location=ts&searchword=%EB%AC%B4%EC%97%AD%EC%97%85%EB%AC%B4&searchType=1&paid_fl=n&search_uuid=bda5d4d8-f57d-4b49-a8fc-e2eebec4d66d",
    "source_site": "사람인",
    "search_keyword": "무역업무",
    "organization_type": "Trading",
    "gtelp_relevance": "Medium-High",
    "collection_date": "2025-10-21",
    "collection_time": "15:27:23"
  },
  {
    "job_title": "해외무역업무(일본어 가능자) / 기계 조립 및 시운전 직원 모집",
    "company_name": "(주)에이스팩",
    "location": "경기",
    "salary": "급여협의",
    "job_url": "https://www.saramin.co.kr/zf_user/jobs/relay/view?view_type=search&rec_idx=52013796&location=ts&searchword=%EB%AC%B4%EC%97%AD%EC%97%85%EB%AC%B4&searchType=1&paid_fl=n&search_uuid=bda5d4d8-f57d-4b49-a8fc-e2eebec4d66d",
    "source_site": "사람인",
    "search_keyword": "무역업무",
    "organization_type": "Trading",
    "gtelp_relevance": "Medium-High",
    "collection_date": "2025-10-21",
    "collection_time": "15:27:23"
  },
  {
    "job_title": "\"종합무역상사",
    "company_name": "중국무역 담당 구인 수출입",
    "location": "물류등무역업무전반\"",
    "salary": "(주)기나글로벌",
    "job_url": "경기",
    "source_site": "급여협의",
    "search_keyword": "https://www.saramin.co.kr/zf_user/jobs/relay/view?view_type=search&rec_idx=51655152&location=ts&searchword=%EB%AC%B4%EC%97%AD%EC%97%85%EB%AC%B4&searchType=1&paid_fl=n&search_uuid=bda5d4d8-f57d-4b49-a8fc-e2eebec4d66d",
    "organization_type": "사람인",
    "gtelp_relevance": "무역업무",
    "collection_date": "Trading",
    "collection_time": "Medium-High"
  },
  {
    "job_title": "(주)정우 해외영업 및무역업무사원 모집- 중국/동남아 Focus",
    "company_name": "(주)정우",
    "location": "부산",
    "salary": "\"3",
    "job_url": "500 만원\"",
    "source_site": "https://www.saramin.co.kr/zf_user/jobs/relay/view?view_type=search&rec_idx=52065241&location=ts&searchword=%EB%AC%B4%EC%97%AD%EC%97%85%EB%AC%B4&searchType=1&paid_fl=n&search_uuid=bda5d4d8-f57d-4b49-a8fc-e2eebec4d66d",
    "search_keyword": "사람인",
    "organization_type": "무역업무",
    "gtelp_relevance": "Trading",
    "collection_date": "Medium-High",
    "collection_time": "2025-10-21"
  },
  {
    "job_title": "반려동물 브랜드 수출입무역업무정규직 채용공고",
    "company_name": "(주)에이플러스",
    "location": "인천",
    "salary": "급여협의",
    "job_url": "https://www.saramin.co.kr/zf_user/jobs/relay/view?view_type=search&rec_idx=52066164&location=ts&searchword=%EB%AC%B4%EC%97%AD%EC%97%85%EB%AC%B4&searchType=1&paid_fl=n&search_uuid=bda5d4d8-f57d-4b49-a8fc-e2eebec4d66d",
    "source_site": "사람인",
    "search_keyword": "무역업무",
    "organization_type": "Trading",
    "gtelp_relevance": "Medium-High",
    "collection_date": "2025-10-21",
    "collection_time": "15:27:23"
  },
  {
    "job_title": "국내 및 해외영업팀 모집(문서작성 및무역업무)",
    "company_name": "(주)카이트코리아",
    "location": "경북",
    "salary": "\"2",
    "job_url": "700 만원\"",
    "source_site": "https://www.saramin.co.kr/zf_user/jobs/relay/view?view_type=search&rec_idx=52096450&location=ts&searchword=%EB%AC%B4%EC%97%AD%EC%97%85%EB%AC%B4&searchType=1&paid_fl=n&search_uuid=bda5d4d8-f57d-4b49-a8fc-e2eebec4d66d",
    "search_keyword": "사람인",
    "organization_type": "무역업무",
    "gtelp_relevance": "Trading",
    "collection_date": "Medium-High",
    "collection_time": "2025-10-21"
  },
  {
    "job_title": "무역업무경력직 채용",
    "company_name": "대광기업(주)",
    "location": "부산",
    "salary": "급여협의",
    "job_url": "https://www.saramin.co.kr/zf_user/jobs/relay/view?view_type=search&rec_idx=51865538&location=ts&searchword=%EB%AC%B4%EC%97%AD%EC%97%85%EB%AC%B4&searchType=1&paid_fl=n&search_uuid=bda5d4d8-f57d-4b49-a8fc-e2eebec4d66d",
    "source_site": "사람인",
    "search_keyword": "무역업무",
    "organization_type": "Trading",
    "gtelp_relevance": "Medium-High",
    "collection_date": "2025-10-21",
    "collection_time": "15:27:23"
  },
  {
    "job_title": "[디오션] 수출무역업무파트타임 근무자 모집",
    "company_name": "(주)디오션",
    "location": "인천",
    "salary": "급여협의",
    "job_url": "https://www.saramin.co.kr/zf_user/jobs/relay/view?view_type=search&rec_idx=51808625&location=ts&searchword=%EB%AC%B4%EC%97%AD%EC%97%85%EB%AC%B4&searchType=1&paid_fl=n&search_uuid=bda5d4d8-f57d-4b49-a8fc-e2eebec4d66d",
    "source_site": "사람인",
    "search_keyword": "무역업무",
    "organization_type": "Trading",
    "gtelp_relevance": "Medium-High",
    "collection_date": "2025-10-21",
    "collection_time": "15:27:23"
  },
  {
    "job_title": "무역업무(거래처 관리) 정규직 채용",
    "company_name": "(주)현대푸드시스템",
    "location": "전남",
    "salary": "급여협의",
    "job_url": "https://www.saramin.co.kr/zf_user/jobs/relay/view?view_type=search&rec_idx=52064314&location=ts&searchword=%EB%AC%B4%EC%97%AD%EC%97%85%EB%AC%B4&searchType=1&paid_fl=n&search_uuid=bda5d4d8-f57d-4b49-a8fc-e2eebec4d66d",
    "source_site": "사람인",
    "search_keyword": "무역업무",
    "organization_type": "Government",
    "gtelp_relevance": "Medium-High",
    "collection_date": "2025-10-21",
    "collection_time": "15:27:23"
  },
  {
    "job_title": "무역업무재고관리/마감/결산업무 경력자 채용",
    "company_name": "(주)씨앤에스",
    "location": "경기",
    "salary": "급여협의",
    "job_url": "https://www.saramin.co.kr/zf_user/jobs/relay/view?view_type=search&rec_idx=51987298&location=ts&searchword=%EB%AC%B4%EC%97%AD%EC%97%85%EB%AC%B4&searchType=1&paid_fl=n&search_uuid=bda5d4d8-f57d-4b49-a8fc-e2eebec4d66d",
    "source_site": "사람인",
    "search_keyword": "무역업무",
    "organization_type": "Trading",
    "gtelp_relevance": "Medium-High",
    "collection_date": "2025-10-21",
    "collection_time": "15:27:23"
  },
  {
    "job_title": "\"해외 수입무역업무",
    "company_name": "영어능통 경력자우대\"",
    "location": "피지에스코리아(주)",
    "salary": "경기",
    "job_url": "\"3",
    "source_site": "800 만원\"",
    "search_keyword": "https://www.saramin.co.kr/zf_user/jobs/relay/view?view_type=search&rec_idx=52044107&location=ts&searchword=%EB%AC%B4%EC%97%AD%EC%97%85%EB%AC%B4&searchType=1&paid_fl=n&search_uuid=bda5d4d8-f57d-4b49-a8fc-e2eebec4d66d",
    "organization_type": "사람인",
    "gtelp_relevance": "무역업무",
    "collection_date": "Trading",
    "collection_time": "Medium-High"
  },
  {
    "job_title": "무역업무경력직원 모집",
    "company_name": "(주)씨앤에스",
    "location": "경기",
    "salary": "급여협의",
    "job_url": "https://www.saramin.co.kr/zf_user/jobs/relay/view?view_type=search&rec_idx=52078410&location=ts&searchword=%EB%AC%B4%EC%97%AD%EC%97%85%EB%AC%B4&searchType=1&paid_fl=n&search_uuid=bda5d4d8-f57d-4b49-a8fc-e2eebec4d66d",
    "source_site": "사람인",
    "search_keyword": "무역업무",
    "organization_type": "Trading",
    "gtelp_relevance": "Medium-High",
    "collection_date": "2025-10-21",
    "collection_time": "15:27:23"
  },
  {
    "job_title": "[인생네컷]해외영업지원 모집",
    "company_name": "(주)엘케이벤쳐스",
    "location": "서울",
    "salary": "급여협의",
    "job_url": "https://www.saramin.co.kr/zf_user/jobs/relay/view?view_type=search&rec_idx=52089138&location=ts&searchword=%ED%95%B4%EC%99%B8%EC%98%81%EC%97%85&searchType=1&paid_fl=y&search_uuid=749104cc-cb42-48d0-b960-362a8f09d3e3",
    "source_site": "사람인",
    "search_keyword": "해외영업",
    "organization_type": "Trading",
    "gtelp_relevance": "Low",
    "collection_date": "2025-10-21",
    "collection_time": "15:27:27"
  },
  {
    "job_title": "\"[콜텍] 각 부문별 신입/경력 채용공고(엠프사업부 회로설계",
    "company_name": "경영지원팀 회계",
    "location": "구매지원팀 구매관리",
    "salary": "해외영업)\"",
    "job_url": "(주)콜텍",
    "source_site": "서울",
    "search_keyword": "급여협의",
    "organization_type": "https://www.saramin.co.kr/zf_user/jobs/relay/view?view_type=search&rec_idx=52070679&location=ts&searchword=%ED%95%B4%EC%99%B8%EC%98%81%EC%97%85&searchType=1&paid_fl=n&search_uuid=749104cc-cb42-48d0-b960-362a8f09d3e3",
    "gtelp_relevance": "사람인",
    "collection_date": "해외영업",
    "collection_time": "Trading"
  },
  {
    "job_title": "해외영업담당자 채용 (신입/경력)",
    "company_name": "(주)윤성에프앤씨",
    "location": "서울",
    "salary": "급여협의",
    "job_url": "https://www.saramin.co.kr/zf_user/jobs/relay/view?view_type=search&rec_idx=52054132&location=ts&searchword=%ED%95%B4%EC%99%B8%EC%98%81%EC%97%85&searchType=1&paid_fl=n&search_uuid=749104cc-cb42-48d0-b960-362a8f09d3e3",
    "source_site": "사람인",
    "search_keyword": "해외영업",
    "organization_type": "Trading",
    "gtelp_relevance": "Low",
    "collection_date": "2025-10-21",
    "collection_time": "15:27:27"
  },
  {
    "job_title": "[동아제약] 화장품해외영업팀장 채용",
    "company_name": "동아제약(주)",
    "location": "서울",
    "salary": "급여협의",
    "job_url": "https://www.saramin.co.kr/zf_user/jobs/relay/view?view_type=search&rec_idx=52086031&location=ts&searchword=%ED%95%B4%EC%99%B8%EC%98%81%EC%97%85&searchType=1&paid_fl=n&search_uuid=749104cc-cb42-48d0-b960-362a8f09d3e3",
    "source_site": "사람인",
    "search_keyword": "해외영업",
    "organization_type": "Trading",
    "gtelp_relevance": "Low",
    "collection_date": "2025-10-21",
    "collection_time": "15:27:27"
  },
  {
    "job_title": "HDXWILL해외영업팀 채용공고",
    "company_name": "에이치디엑스(주)",
    "location": "서울",
    "salary": "급여협의",
    "job_url": "https://www.saramin.co.kr/zf_user/jobs/relay/view?view_type=search&rec_idx=52043428&location=ts&searchword=%ED%95%B4%EC%99%B8%EC%98%81%EC%97%85&searchType=1&paid_fl=n&search_uuid=749104cc-cb42-48d0-b960-362a8f09d3e3",
    "source_site": "사람인",
    "search_keyword": "해외영업",
    "organization_type": "Trading",
    "gtelp_relevance": "Low",
    "collection_date": "2025-10-21",
    "collection_time": "15:27:27"
  },
  {
    "job_title": "[삼진어묵]해외영업팀 팀장 채용",
    "company_name": "삼진식품(주)",
    "location": "서울",
    "salary": "급여협의",
    "job_url": "https://www.saramin.co.kr/zf_user/jobs/relay/view?view_type=search&rec_idx=52053238&location=ts&searchword=%ED%95%B4%EC%99%B8%EC%98%81%EC%97%85&searchType=1&paid_fl=n&search_uuid=749104cc-cb42-48d0-b960-362a8f09d3e3",
    "source_site": "사람인",
    "search_keyword": "해외영업",
    "organization_type": "Trading",
    "gtelp_relevance": "Low",
    "collection_date": "2025-10-21",
    "collection_time": "15:27:27"
  },
  {
    "job_title": "[삼진어묵]해외영업팀 중화권 담당자 채용",
    "company_name": "삼진식품(주)",
    "location": "서울",
    "salary": "급여협의",
    "job_url": "https://www.saramin.co.kr/zf_user/jobs/relay/view?view_type=search&rec_idx=52053188&location=ts&searchword=%ED%95%B4%EC%99%B8%EC%98%81%EC%97%85&searchType=1&paid_fl=n&search_uuid=749104cc-cb42-48d0-b960-362a8f09d3e3",
    "source_site": "사람인",
    "search_keyword": "해외영업",
    "organization_type": "Trading",
    "gtelp_relevance": "Low",
    "collection_date": "2025-10-21",
    "collection_time": "15:27:27"
  },
  {
    "job_title": "대림통상(주) 2025년해외영업(일본팀) 모집",
    "company_name": "대림통상(주)",
    "location": "서울",
    "salary": "급여협의",
    "job_url": "https://www.saramin.co.kr/zf_user/jobs/relay/view?view_type=search&rec_idx=52059112&location=ts&searchword=%ED%95%B4%EC%99%B8%EC%98%81%EC%97%85&searchType=1&paid_fl=n&search_uuid=749104cc-cb42-48d0-b960-362a8f09d3e3",
    "source_site": "사람인",
    "search_keyword": "해외영업",
    "organization_type": "Trading",
    "gtelp_relevance": "Low",
    "collection_date": "2025-10-21",
    "collection_time": "15:27:27"
  },
  {
    "job_title": "\"본사 각 부문별 채용(초음파",
    "company_name": "연구소",
    "location": "해외영업)\"",
    "salary": "(주)디알젬",
    "job_url": "경기",
    "source_site": "급여협의",
    "search_keyword": "https://www.saramin.co.kr/zf_user/jobs/relay/view?view_type=search&rec_idx=51919519&location=ts&searchword=%ED%95%B4%EC%99%B8%EC%98%81%EC%97%85&searchType=1&paid_fl=n&search_uuid=749104cc-cb42-48d0-b960-362a8f09d3e3",
    "organization_type": "사람인",
    "gtelp_relevance": "해외영업",
    "collection_date": "Trading",
    "collection_time": "Low"
  },
  {
    "job_title": "중국 주재해외영업/ 제품개발 사원 모집",
    "company_name": "(주)한국가스스프링",
    "location": "전국",
    "salary": "급여협의",
    "job_url": "https://www.saramin.co.kr/zf_user/jobs/relay/view?view_type=search&rec_idx=51969507&location=ts&searchword=%ED%95%B4%EC%99%B8%EC%98%81%EC%97%85&searchType=1&paid_fl=n&search_uuid=749104cc-cb42-48d0-b960-362a8f09d3e3",
    "source_site": "사람인",
    "search_keyword": "해외영업",
    "organization_type": "Trading",
    "gtelp_relevance": "Low",
    "collection_date": "2025-10-21",
    "collection_time": "15:27:27"
  },
  {
    "job_title": "해외영업부(스포츠 전문)신입/경력직 채용",
    "company_name": "윈엔윈(주)",
    "location": "경기",
    "salary": "급여협의",
    "job_url": "https://www.saramin.co.kr/zf_user/jobs/relay/view?view_type=search&rec_idx=52081876&location=ts&searchword=%ED%95%B4%EC%99%B8%EC%98%81%EC%97%85&searchType=1&paid_fl=n&search_uuid=749104cc-cb42-48d0-b960-362a8f09d3e3",
    "source_site": "사람인",
    "search_keyword": "해외영업",
    "organization_type": "Trading",
    "gtelp_relevance": "Low",
    "collection_date": "2025-10-21",
    "collection_time": "15:27:27"
  },
  {
    "job_title": "\"[최신물산]해외영업MR 신입 채용(사원급) EXPRESS",
    "company_name": "QVC\"",
    "location": "최신물산(주)",
    "salary": "서울",
    "job_url": "급여협의",
    "source_site": "https://www.saramin.co.kr/zf_user/jobs/relay/view?view_type=search&rec_idx=52083646&location=ts&searchword=%ED%95%B4%EC%99%B8%EC%98%81%EC%97%85&searchType=1&paid_fl=n&search_uuid=749104cc-cb42-48d0-b960-362a8f09d3e3",
    "search_keyword": "사람인",
    "organization_type": "해외영업",
    "gtelp_relevance": "Trading",
    "collection_date": "Low",
    "collection_time": "2025-10-21"
  },
  {
    "job_title": "해외영업무역사무원 정규직 모집",
    "company_name": "(주)보성엔지니어링",
    "location": "부산",
    "salary": "\"3",
    "job_url": "500 만원\"",
    "source_site": "https://www.saramin.co.kr/zf_user/jobs/relay/view?view_type=search&rec_idx=52018323&location=ts&searchword=%ED%95%B4%EC%99%B8%EC%98%81%EC%97%85&searchType=1&paid_fl=n&search_uuid=749104cc-cb42-48d0-b960-362a8f09d3e3",
    "search_keyword": "사람인",
    "organization_type": "해외영업",
    "gtelp_relevance": "Trading",
    "collection_date": "Medium-High",
    "collection_time": "2025-10-21"
  },
  {
    "job_title": "[의료기기]해외영업(메디컬/덴탈치과) 및 영업지원 정규직 모집",
    "company_name": "(주)제노레이",
    "location": "서울",
    "salary": "급여협의",
    "job_url": "https://www.saramin.co.kr/zf_user/jobs/relay/view?view_type=search&rec_idx=51709684&location=ts&searchword=%ED%95%B4%EC%99%B8%EC%98%81%EC%97%85&searchType=1&paid_fl=n&search_uuid=749104cc-cb42-48d0-b960-362a8f09d3e3",
    "source_site": "사람인",
    "search_keyword": "해외영업",
    "organization_type": "Trading",
    "gtelp_relevance": "Low",
    "collection_date": "2025-10-21",
    "collection_time": "15:27:27"
  },
  {
    "job_title": "(주)이노폴해외영업팀원 채용(신입 4100~)",
    "company_name": "(주)이노폴",
    "location": "부산",
    "salary": "\"4",
    "job_url": "100 만원\"",
    "source_site": "https://www.saramin.co.kr/zf_user/jobs/relay/view?view_type=search&rec_idx=52088310&location=ts&searchword=%ED%95%B4%EC%99%B8%EC%98%81%EC%97%85&searchType=1&paid_fl=n&search_uuid=749104cc-cb42-48d0-b960-362a8f09d3e3",
    "search_keyword": "사람인",
    "organization_type": "해외영업",
    "gtelp_relevance": "Trading",
    "collection_date": "Low",
    "collection_time": "2025-10-21"
  },
  {
    "job_title": "[잠실/Lynxeo Korea] Power팀해외영업지원 (정규직)",
    "company_name": "링세오코리아(주)",
    "location": "서울",
    "salary": "급여협의",
    "job_url": "https://www.saramin.co.kr/zf_user/jobs/relay/view?view_type=search&rec_idx=51877648&location=ts&searchword=%ED%95%B4%EC%99%B8%EC%98%81%EC%97%85&searchType=1&paid_fl=n&search_uuid=749104cc-cb42-48d0-b960-362a8f09d3e3",
    "source_site": "사람인",
    "search_keyword": "해외영업",
    "organization_type": "Trading",
    "gtelp_relevance": "Low",
    "collection_date": "2025-10-21",
    "collection_time": "15:27:27"
  },
  {
    "job_title": "동아시아(일본 등)해외영업담당자 모집",
    "company_name": "삼덕통상(주)",
    "location": "부산",
    "salary": "급여협의",
    "job_url": "https://www.saramin.co.kr/zf_user/jobs/relay/view?view_type=search&rec_idx=52080227&location=ts&searchword=%ED%95%B4%EC%99%B8%EC%98%81%EC%97%85&searchType=1&paid_fl=n&search_uuid=749104cc-cb42-48d0-b960-362a8f09d3e3",
    "source_site": "사람인",
    "search_keyword": "해외영업",
    "organization_type": "Trading",
    "gtelp_relevance": "Low",
    "collection_date": "2025-10-21",
    "collection_time": "15:27:27"
  },
  {
    "job_title": "[영어] 신라호텔 고객지원센터 문의 상담 Md9C",
    "company_name": "(주)트랜스코스모스코리아",
    "location": "서울",
    "salary": "\"3",
    "job_url": "200 만원\"",
    "source_site": "https://www.saramin.co.kr/zf_user/jobs/relay/view?view_type=search&rec_idx=51926172&location=ts&searchword=%EC%98%81%EC%96%B4%EB%8A%A5%EB%A0%A5%ED%8F%89%EA%B0%80&searchType=1&paid_fl=n&search_uuid=8fb08cd7-f6e6-4180-9da8-24015308ec9e",
    "search_keyword": "사람인",
    "organization_type": "영어능력평가",
    "gtelp_relevance": "Others",
    "collection_date": "Medium",
    "collection_time": "2025-10-21"
  },
  {
    "job_title": "영어강사 신입/경력 채용",
    "company_name": "제이엔에스아카데미(주)",
    "location": "광주",
    "salary": "50만원",
    "job_url": "https://www.saramin.co.kr/zf_user/jobs/relay/view?view_type=search&rec_idx=51766414&location=ts&searchword=%EC%98%81%EC%96%B4%EB%8A%A5%EB%A0%A5%ED%8F%89%EA%B0%80&searchType=1&paid_fl=n&search_uuid=8fb08cd7-f6e6-4180-9da8-24015308ec9e",
    "source_site": "사람인",
    "search_keyword": "영어능력평가",
    "organization_type": "Others",
    "gtelp_relevance": "Medium",
    "collection_date": "2025-10-21",
    "collection_time": "15:27:34"
  },
  {
    "job_title": "영어강사 신입 채용",
    "company_name": "제이엔에스아카데미(주)",
    "location": "광주",
    "salary": "50만원",
    "job_url": "https://www.saramin.co.kr/zf_user/jobs/relay/view?view_type=search&rec_idx=51772138&location=ts&searchword=%EC%98%81%EC%96%B4%EB%8A%A5%EB%A0%A5%ED%8F%89%EA%B0%80&searchType=1&paid_fl=n&search_uuid=8fb08cd7-f6e6-4180-9da8-24015308ec9e",
    "source_site": "사람인",
    "search_keyword": "영어능력평가",
    "organization_type": "Others",
    "gtelp_relevance": "Medium",
    "collection_date": "2025-10-21",
    "collection_time": "15:27:34"
  },
  {
    "job_title": "영어강사 경력직 채용",
    "company_name": "제이엔에스아카데미(주)",
    "location": "광주",
    "salary": "50만원",
    "job_url": "https://www.saramin.co.kr/zf_user/jobs/relay/view?view_type=search&rec_idx=51772168&location=ts&searchword=%EC%98%81%EC%96%B4%EB%8A%A5%EB%A0%A5%ED%8F%89%EA%B0%80&searchType=1&paid_fl=n&search_uuid=8fb08cd7-f6e6-4180-9da8-24015308ec9e",
    "source_site": "사람인",
    "search_keyword": "영어능력평가",
    "organization_type": "Others",
    "gtelp_relevance": "Medium",
    "collection_date": "2025-10-21",
    "collection_time": "15:27:34"
  },
  {
    "job_title": "(주)나주수산 무역수출입 및 국내영업 신입 모집(영어회화필)",
    "company_name": "(주)나주수산",
    "location": "부산",
    "salary": "\"3",
    "job_url": "400 만원\"",
    "source_site": "https://www.saramin.co.kr/zf_user/jobs/relay/view?view_type=search&rec_idx=51995084&location=ts&searchword=%EC%98%81%EC%96%B4%ED%9A%8C%ED%99%94&searchType=1&paid_fl=n&search_uuid=a41962fb-2750-46c7-9e31-ce77aa006d09",
    "search_keyword": "사람인",
    "organization_type": "영어회화",
    "gtelp_relevance": "Trading",
    "collection_date": "Medium-High",
    "collection_time": "2025-10-21"
  },
  {
    "job_title": "[압구정센터] 1:1영어회화학원 오전 교육컨설턴트 채용[풀타임]",
    "company_name": "랭귀지큐브 역삼",
    "location": "서울",
    "salary": "급여협의",
    "job_url": "https://www.saramin.co.kr/zf_user/jobs/relay/view?view_type=search&rec_idx=52079870&location=ts&searchword=%EC%98%81%EC%96%B4%ED%9A%8C%ED%99%94&searchType=1&paid_fl=n&search_uuid=a41962fb-2750-46c7-9e31-ce77aa006d09",
    "source_site": "사람인",
    "search_keyword": "영어회화",
    "organization_type": "Others",
    "gtelp_relevance": "Medium",
    "collection_date": "2025-10-21",
    "collection_time": "15:27:38"
  },
  {
    "job_title": "인천송도 국제학교 행정실 교직원 채용함.(영어회화필수)",
    "company_name": "제이아이씨에스어학원",
    "location": "인천",
    "salary": "\"2",
    "job_url": "900 만원\"",
    "source_site": "https://www.saramin.co.kr/zf_user/jobs/relay/view?view_type=search&rec_idx=52072718&location=ts&searchword=%EC%98%81%EC%96%B4%ED%9A%8C%ED%99%94&searchType=1&paid_fl=n&search_uuid=a41962fb-2750-46c7-9e31-ce77aa006d09",
    "search_keyword": "사람인",
    "organization_type": "영어회화",
    "gtelp_relevance": "University",
    "collection_date": "Medium",
    "collection_time": "2025-10-21"
  },
  {
    "job_title": "해외영업관련  인원모집(영어회화가능자 우대)",
    "company_name": "(주)코마텍",
    "location": "대구",
    "salary": "급여협의",
    "job_url": "https://www.saramin.co.kr/zf_user/jobs/relay/view?view_type=search&rec_idx=51899204&location=ts&searchword=%EC%98%81%EC%96%B4%ED%9A%8C%ED%99%94&searchType=1&paid_fl=n&search_uuid=a41962fb-2750-46c7-9e31-ce77aa006d09",
    "source_site": "사람인",
    "search_keyword": "영어회화",
    "organization_type": "Trading",
    "gtelp_relevance": "Medium",
    "collection_date": "2025-10-21",
    "collection_time": "15:27:38"
  },
  {
    "job_title": "(주)나주수산 무역수출입 및 국내영업 경력직 모집(영어회화필)",
    "company_name": "(주)나주수산",
    "location": "부산",
    "salary": "급여협의",
    "job_url": "https://www.saramin.co.kr/zf_user/jobs/relay/view?view_type=search&rec_idx=51995114&location=ts&searchword=%EC%98%81%EC%96%B4%ED%9A%8C%ED%99%94&searchType=1&paid_fl=n&search_uuid=a41962fb-2750-46c7-9e31-ce77aa006d09",
    "source_site": "사람인",
    "search_keyword": "영어회화",
    "organization_type": "Trading",
    "gtelp_relevance": "Medium-High",
    "collection_date": "2025-10-21",
    "collection_time": "15:27:38"
  },
  {
    "job_title": "[경력/영어회화가능] 임원비서 채용",
    "company_name": "(주)리팅랩스",
    "location": "서울",
    "salary": "급여협의",
    "job_url": "https://www.saramin.co.kr/zf_user/jobs/relay/view?view_type=search&rec_idx=52015052&location=ts&searchword=%EC%98%81%EC%96%B4%ED%9A%8C%ED%99%94&searchType=1&paid_fl=n&search_uuid=a41962fb-2750-46c7-9e31-ce77aa006d09",
    "source_site": "사람인",
    "search_keyword": "영어회화",
    "organization_type": "Others",
    "gtelp_relevance": "Medium",
    "collection_date": "2025-10-21",
    "collection_time": "15:27:38"
  },
  {
    "job_title": "[압구정센터] 1:1영어회화학원 오전 교육컨설턴트 채용",
    "company_name": "랭귀지큐브 역삼",
    "location": "서울",
    "salary": "급여협의",
    "job_url": "https://www.saramin.co.kr/zf_user/jobs/relay/view?view_type=search&rec_idx=52010059&location=ts&searchword=%EC%98%81%EC%96%B4%ED%9A%8C%ED%99%94&searchType=1&paid_fl=n&search_uuid=a41962fb-2750-46c7-9e31-ce77aa006d09",
    "source_site": "사람인",
    "search_keyword": "영어회화",
    "organization_type": "Others",
    "gtelp_relevance": "Medium",
    "collection_date": "2025-10-21",
    "collection_time": "15:27:38"
  },
  {
    "job_title": "\"온라인영어회화수강생 관리 플래너 모집 (재택근무",
    "company_name": "부업가능)\"",
    "location": "애나잉글리쉬 울산점",
    "salary": "서울",
    "job_url": "급여협의",
    "source_site": "https://www.saramin.co.kr/zf_user/jobs/relay/view?view_type=search&rec_idx=51829500&location=ts&searchword=%EC%98%81%EC%96%B4%ED%9A%8C%ED%99%94&searchType=1&paid_fl=n&search_uuid=a41962fb-2750-46c7-9e31-ce77aa006d09",
    "search_keyword": "사람인",
    "organization_type": "영어회화",
    "gtelp_relevance": "Others",
    "collection_date": "Medium",
    "collection_time": "2025-10-21"
  },
  {
    "job_title": "초등영어회화및  중등문법 채용",
    "company_name": "지앤비어학&자이수학학원",
    "location": "경남",
    "salary": "급여협의",
    "job_url": "https://www.saramin.co.kr/zf_user/jobs/relay/view?view_type=search&rec_idx=52030101&location=ts&searchword=%EC%98%81%EC%96%B4%ED%9A%8C%ED%99%94&searchType=1&paid_fl=n&search_uuid=a41962fb-2750-46c7-9e31-ce77aa006d09",
    "source_site": "사람인",
    "search_keyword": "영어회화",
    "organization_type": "Others",
    "gtelp_relevance": "Medium",
    "collection_date": "2025-10-21",
    "collection_time": "15:27:38"
  },
  {
    "job_title": "외국어·어학원(영어&영어회화) 모집",
    "company_name": "eie 고려대국제어학원 검단신도시어학원",
    "location": "인천",
    "salary": "340 만원",
    "job_url": "https://www.saramin.co.kr/zf_user/jobs/relay/view?view_type=search&rec_idx=52072706&location=ts&searchword=%EC%98%81%EC%96%B4%ED%9A%8C%ED%99%94&searchType=1&paid_fl=n&search_uuid=a41962fb-2750-46c7-9e31-ce77aa006d09",
    "source_site": "사람인",
    "search_keyword": "영어회화",
    "organization_type": "Others",
    "gtelp_relevance": "Medium",
    "collection_date": "2025-10-21",
    "collection_time": "15:27:38"
  },
  {
    "job_title": "국제학교 office head 송도 캠퍼스 모집(영어회화필수)",
    "company_name": "제이아이씨에스어학원",
    "location": "인천",
    "salary": "300 만원",
    "job_url": "https://www.saramin.co.kr/zf_user/jobs/relay/view?view_type=search&rec_idx=52072725&location=ts&searchword=%EC%98%81%EC%96%B4%ED%9A%8C%ED%99%94&searchType=1&paid_fl=n&search_uuid=a41962fb-2750-46c7-9e31-ce77aa006d09",
    "source_site": "사람인",
    "search_keyword": "영어회화",
    "organization_type": "University",
    "gtelp_relevance": "Medium",
    "collection_date": "2025-10-21",
    "collection_time": "15:27:38"
  },
  {
    "job_title": "제이잉글리쉬어학원영어회화수업 강사 모집",
    "company_name": "제이잉글리쉬어학원",
    "location": "경북",
    "salary": "급여협의",
    "job_url": "https://www.saramin.co.kr/zf_user/jobs/relay/view?view_type=search&rec_idx=52072254&location=ts&searchword=%EC%98%81%EC%96%B4%ED%9A%8C%ED%99%94&searchType=1&paid_fl=n&search_uuid=a41962fb-2750-46c7-9e31-ce77aa006d09",
    "source_site": "사람인",
    "search_keyword": "영어회화",
    "organization_type": "Others",
    "gtelp_relevance": "Medium",
    "collection_date": "2025-10-21",
    "collection_time": "15:27:38"
  },
  {
    "job_title": "영어회화가능자 / 시스템엔지니어 채용",
    "company_name": "(주)아이티시스템즈",
    "location": "서울",
    "salary": "급여협의",
    "job_url": "https://www.saramin.co.kr/zf_user/jobs/relay/view?view_type=search&rec_idx=51959552&location=ts&searchword=%EC%98%81%EC%96%B4%ED%9A%8C%ED%99%94&searchType=1&paid_fl=n&search_uuid=a41962fb-2750-46c7-9e31-ce77aa006d09",
    "source_site": "사람인",
    "search_keyword": "영어회화",
    "organization_type": "Others",
    "gtelp_relevance": "Medium",
    "collection_date": "2025-10-21",
    "collection_time": "15:27:38"
  },
  {
    "job_title": "기술영업 경력자 채용 중 (영어회화필수)",
    "company_name": "(주)아펠",
    "location": "경기",
    "salary": "급여협의",
    "job_url": "https://www.saramin.co.kr/zf_user/jobs/relay/view?view_type=search&rec_idx=51939697&location=ts&searchword=%EC%98%81%EC%96%B4%ED%9A%8C%ED%99%94&searchType=1&paid_fl=n&search_uuid=a41962fb-2750-46c7-9e31-ce77aa006d09",
    "source_site": "사람인",
    "search_keyword": "영어회화",
    "organization_type": "IT_Tech",
    "gtelp_relevance": "Medium",
    "collection_date": "2025-10-21",
    "collection_time": "15:27:38"
  },
  {
    "job_title": "\"전장설계 및 PLC 엔지니어 채용 공고(미국 출장가능자",
    "company_name": "영어회화)\"",
    "location": "(주)명성오토메이션",
    "salary": "경기",
    "job_url": "급여협의",
    "source_site": "https://www.saramin.co.kr/zf_user/jobs/relay/view?view_type=search&rec_idx=51970874&location=ts&searchword=%EC%98%81%EC%96%B4%ED%9A%8C%ED%99%94&searchType=1&paid_fl=n&search_uuid=a41962fb-2750-46c7-9e31-ce77aa006d09",
    "search_keyword": "사람인",
    "organization_type": "영어회화",
    "gtelp_relevance": "Others",
    "collection_date": "Medium",
    "collection_time": "2025-10-21"
  },
  {
    "job_title": "\"예원예술대학교 양주",
    "company_name": "임실 국제 계약직(영어회화가능자) 채용\"",
    "location": "예원예술대학교",
    "salary": "경기",
    "job_url": "급여협의",
    "source_site": "https://www.saramin.co.kr/zf_user/jobs/relay/view?view_type=search&rec_idx=51689020&location=ts&searchword=%EC%98%81%EC%96%B4%ED%9A%8C%ED%99%94&searchType=1&paid_fl=n&search_uuid=a41962fb-2750-46c7-9e31-ce77aa006d09",
    "search_keyword": "사람인",
    "organization_type": "영어회화",
    "gtelp_relevance": "University",
    "collection_date": "Medium",
    "collection_time": "2025-10-21"
  },
  {
    "job_title": "[퍼스널잉글리쉬 강남센터]  일대일영어회화강사 채용",
    "company_name": "주)퍼스널캠퍼스",
    "location": "서울",
    "salary": "급여협의",
    "job_url": "https://www.saramin.co.kr/zf_user/jobs/relay/view?view_type=search&rec_idx=51902671&location=ts&searchword=%EC%98%81%EC%96%B4%ED%9A%8C%ED%99%94&searchType=1&paid_fl=n&search_uuid=a41962fb-2750-46c7-9e31-ce77aa006d09",
    "source_site": "사람인",
    "search_keyword": "영어회화",
    "organization_type": "Others",
    "gtelp_relevance": "Medium",
    "collection_date": "2025-10-21",
    "collection_time": "15:27:38"
  }
]